{
"meta":{"test_sets":[],"test_metrics":[],"learn_metrics":[{"best_value":"Min","name":"RMSE"}],"launch_mode":"Train","parameters":"","iteration_count":1000,"learn_sets":["learn"],"name":"experiment"},
"iterations":[
{"learn":[14.61268541],"iteration":0,"passed_time":0.1481379457,"remaining_time":147.9898077},
{"learn":[14.23196558],"iteration":1,"passed_time":0.1489541878,"remaining_time":74.3281397},
{"learn":[13.86674177],"iteration":2,"passed_time":0.1496364435,"remaining_time":49.72917805},
{"learn":[13.49946468],"iteration":3,"passed_time":0.1502840128,"remaining_time":37.42071919},
{"learn":[13.16661202],"iteration":4,"passed_time":0.1509367921,"remaining_time":30.03642162},
{"learn":[12.85632158],"iteration":5,"passed_time":0.1515628903,"remaining_time":25.10891883},
{"learn":[12.56784336],"iteration":6,"passed_time":0.1521848807,"remaining_time":21.58851236},
{"learn":[12.31617801],"iteration":7,"passed_time":0.1527979139,"remaining_time":18.94694132},
{"learn":[12.01509946],"iteration":8,"passed_time":0.1533961989,"remaining_time":16.8906259},
{"learn":[11.71512571],"iteration":9,"passed_time":0.1540014873,"remaining_time":15.24614724},
{"learn":[11.43264457],"iteration":10,"passed_time":0.1545976182,"remaining_time":13.8997313},
{"learn":[11.17973129],"iteration":11,"passed_time":0.1552194783,"remaining_time":12.77973704},
{"learn":[10.93746433],"iteration":12,"passed_time":0.1558238048,"remaining_time":11.83062272},
{"learn":[10.69387075],"iteration":13,"passed_time":0.156434183,"remaining_time":11.01743603},
{"learn":[10.4615922],"iteration":14,"passed_time":0.1570751897,"remaining_time":10.31460412},
{"learn":[10.2299235],"iteration":15,"passed_time":0.1577015885,"remaining_time":9.698647694},
{"learn":[10.01419731],"iteration":16,"passed_time":0.1583190302,"remaining_time":9.154565098},
{"learn":[9.795856918],"iteration":17,"passed_time":0.1589478536,"remaining_time":8.671488458},
{"learn":[9.60040151],"iteration":18,"passed_time":0.1595628907,"remaining_time":8.238483987},
{"learn":[9.418664989],"iteration":19,"passed_time":0.1601664858,"remaining_time":7.848157805},
{"learn":[9.249278645],"iteration":20,"passed_time":0.1607739885,"remaining_time":7.495130224},
{"learn":[9.090113396],"iteration":21,"passed_time":0.1613879334,"remaining_time":7.174427222},
{"learn":[8.909548708],"iteration":22,"passed_time":0.1619893143,"remaining_time":6.881024353},
{"learn":[8.740140208],"iteration":23,"passed_time":0.1625938814,"remaining_time":6.612151175},
{"learn":[8.59377682],"iteration":24,"passed_time":0.1632119743,"remaining_time":6.365266996},
{"learn":[8.453885414],"iteration":25,"passed_time":0.1638241659,"remaining_time":6.137105291},
{"learn":[8.317732234],"iteration":26,"passed_time":0.164425677,"remaining_time":5.925414213},
{"learn":[8.180896085],"iteration":27,"passed_time":0.1650251744,"remaining_time":5.728731053},
{"learn":[8.053220863],"iteration":28,"passed_time":0.1656240004,"remaining_time":5.545548427},
{"learn":[7.924234474],"iteration":29,"passed_time":0.1662371639,"remaining_time":5.375001631},
{"learn":[7.818879511],"iteration":30,"passed_time":0.166850658,"remaining_time":5.215428631},
{"learn":[7.719346395],"iteration":31,"passed_time":0.1674813249,"remaining_time":5.066310079},
{"learn":[7.624163594],"iteration":32,"passed_time":0.1680934865,"remaining_time":4.925648528},
{"learn":[7.524952543],"iteration":33,"passed_time":0.1686983441,"remaining_time":4.793017658},
{"learn":[7.424464745],"iteration":34,"passed_time":0.1692944849,"remaining_time":4.667690799},
{"learn":[7.327482321],"iteration":35,"passed_time":0.1699002743,"remaining_time":4.54955179},
{"learn":[7.238666841],"iteration":36,"passed_time":0.1705174254,"remaining_time":4.43806164},
{"learn":[7.158842395],"iteration":37,"passed_time":0.1711552861,"remaining_time":4.332931191},
{"learn":[7.074348246],"iteration":38,"passed_time":0.171749313,"remaining_time":4.232079225},
{"learn":[6.992269093],"iteration":39,"passed_time":0.1723475679,"remaining_time":4.13634163},
{"learn":[6.925219745],"iteration":40,"passed_time":0.1729499808,"remaining_time":4.045342234},
{"learn":[6.86013671],"iteration":41,"passed_time":0.1735645971,"remaining_time":3.958925809},
{"learn":[6.786739622],"iteration":42,"passed_time":0.17416705,"remaining_time":3.876229462},
{"learn":[6.73057926],"iteration":43,"passed_time":0.1747730598,"remaining_time":3.797341936},
{"learn":[6.666356486],"iteration":44,"passed_time":0.1753726774,"remaining_time":3.721797931},
{"learn":[6.606182832],"iteration":45,"passed_time":0.1759986153,"remaining_time":3.650058239},
{"learn":[6.547854615],"iteration":46,"passed_time":0.1765891154,"remaining_time":3.580626105},
{"learn":[6.49240675],"iteration":47,"passed_time":0.1772036815,"remaining_time":3.514539684},
{"learn":[6.431317261],"iteration":48,"passed_time":0.1778245397,"remaining_time":3.451247699},
{"learn":[6.377586395],"iteration":49,"passed_time":0.1784368916,"remaining_time":3.390300941},
{"learn":[6.327558015],"iteration":50,"passed_time":0.1790398756,"remaining_time":3.331545921},
{"learn":[6.282040317],"iteration":51,"passed_time":0.1796458453,"remaining_time":3.275081949},
{"learn":[6.237655841],"iteration":52,"passed_time":0.1802381288,"remaining_time":3.220481283},
{"learn":[6.192792003],"iteration":53,"passed_time":0.1808406319,"remaining_time":3.168059959},
{"learn":[6.150579347],"iteration":54,"passed_time":0.181438957,"remaining_time":3.11745117},
{"learn":[6.115693845],"iteration":55,"passed_time":0.1820406485,"remaining_time":3.068685217},
{"learn":[6.078780782],"iteration":56,"passed_time":0.1826466482,"remaining_time":3.021680514},
{"learn":[6.045146957],"iteration":57,"passed_time":0.1832726363,"remaining_time":2.976600403},
{"learn":[6.008080327],"iteration":58,"passed_time":0.1838938251,"remaining_time":2.932950668},
{"learn":[5.977575734],"iteration":59,"passed_time":0.1845002056,"remaining_time":2.890503221},
{"learn":[5.948036502],"iteration":60,"passed_time":0.1851681038,"remaining_time":2.850374581},
{"learn":[5.914888282],"iteration":61,"passed_time":0.1858731832,"remaining_time":2.812081384},
{"learn":[5.884957796],"iteration":62,"passed_time":0.1865011951,"remaining_time":2.773835234},
{"learn":[5.849539885],"iteration":63,"passed_time":0.1871393063,"remaining_time":2.736912354},
{"learn":[5.821387627],"iteration":64,"passed_time":0.1877947006,"remaining_time":2.701354539},
{"learn":[5.797012279],"iteration":65,"passed_time":0.1884145368,"remaining_time":2.666351172},
{"learn":[5.768685095],"iteration":66,"passed_time":0.1890244741,"remaining_time":2.632236333},
{"learn":[5.755484587],"iteration":67,"passed_time":0.1893612887,"remaining_time":2.595363545},
{"learn":[5.731887055],"iteration":68,"passed_time":0.1900402581,"remaining_time":2.564166381},
{"learn":[5.707148487],"iteration":69,"passed_time":0.1908275749,"remaining_time":2.535280637},
{"learn":[5.685365039],"iteration":70,"passed_time":0.191619811,"remaining_time":2.507250767},
{"learn":[5.663541834],"iteration":71,"passed_time":0.192437516,"remaining_time":2.480305761},
{"learn":[5.638108797],"iteration":72,"passed_time":0.1932006364,"remaining_time":2.453383424},
{"learn":[5.619204893],"iteration":73,"passed_time":0.1938737546,"remaining_time":2.426041848},
{"learn":[5.598472793],"iteration":74,"passed_time":0.1945812987,"remaining_time":2.399836018},
{"learn":[5.577007075],"iteration":75,"passed_time":0.1953740359,"remaining_time":2.375336962},
{"learn":[5.562637084],"iteration":76,"passed_time":0.1961664323,"remaining_time":2.351449572},
{"learn":[5.54729991],"iteration":77,"passed_time":0.1969217378,"remaining_time":2.327715927},
{"learn":[5.530737623],"iteration":78,"passed_time":0.1976957792,"remaining_time":2.304782439},
{"learn":[5.513704873],"iteration":79,"passed_time":0.1984270788,"remaining_time":2.281911406},
{"learn":[5.501575529],"iteration":80,"passed_time":0.1990754696,"remaining_time":2.258646378},
{"learn":[5.484080734],"iteration":81,"passed_time":0.1996895549,"remaining_time":2.235548919},
{"learn":[5.472178894],"iteration":82,"passed_time":0.200351131,"remaining_time":2.213517917},
{"learn":[5.458923342],"iteration":83,"passed_time":0.2009617496,"remaining_time":2.191440031},
{"learn":[5.451382371],"iteration":84,"passed_time":0.2013786074,"remaining_time":2.167781479},
{"learn":[5.441410748],"iteration":85,"passed_time":0.2020045152,"remaining_time":2.146885197},
{"learn":[5.434047468],"iteration":86,"passed_time":0.2024238778,"remaining_time":2.124287361},
{"learn":[5.422107497],"iteration":87,"passed_time":0.2030610673,"remaining_time":2.104451061},
{"learn":[5.40731265],"iteration":88,"passed_time":0.2036864241,"remaining_time":2.084925082},
{"learn":[5.396360181],"iteration":89,"passed_time":0.2043136945,"remaining_time":2.065838467},
{"learn":[5.383793239],"iteration":90,"passed_time":0.2049569456,"remaining_time":2.047317182},
{"learn":[5.369605034],"iteration":91,"passed_time":0.2055899771,"remaining_time":2.029083687},
{"learn":[5.357467333],"iteration":92,"passed_time":0.206216456,"remaining_time":2.011164792},
{"learn":[5.341109968],"iteration":93,"passed_time":0.2068327956,"remaining_time":1.993516094},
{"learn":[5.330529276],"iteration":94,"passed_time":0.2075425135,"remaining_time":1.977115524},
{"learn":[5.319862075],"iteration":95,"passed_time":0.208217525,"remaining_time":1.960715027},
{"learn":[5.313052243],"iteration":96,"passed_time":0.2088629803,"remaining_time":1.944363621},
{"learn":[5.299677207],"iteration":97,"passed_time":0.2095639625,"remaining_time":1.928843818},
{"learn":[5.287546698],"iteration":98,"passed_time":0.2106024794,"remaining_time":1.916695292},
{"learn":[5.279803754],"iteration":99,"passed_time":0.2113622634,"remaining_time":1.902260371},
{"learn":[5.272254612],"iteration":100,"passed_time":0.2120651762,"remaining_time":1.887590033},
{"learn":[5.268813888],"iteration":101,"passed_time":0.2124421276,"remaining_time":1.870323829},
{"learn":[5.258113767],"iteration":102,"passed_time":0.213144049,"remaining_time":1.85621565},
{"learn":[5.251018576],"iteration":103,"passed_time":0.214012425,"remaining_time":1.843799354},
{"learn":[5.24171237],"iteration":104,"passed_time":0.2147388051,"remaining_time":1.830392672},
{"learn":[5.233984943],"iteration":105,"passed_time":0.2156289233,"remaining_time":1.818606202},
{"learn":[5.226240449],"iteration":106,"passed_time":0.2164687809,"remaining_time":1.806603938},
{"learn":[5.220541644],"iteration":107,"passed_time":0.2171141557,"remaining_time":1.793202101},
{"learn":[5.211712096],"iteration":108,"passed_time":0.2179145525,"remaining_time":1.781301526},
{"learn":[5.203388597],"iteration":109,"passed_time":0.218571069,"remaining_time":1.768438649},
{"learn":[5.196026544],"iteration":110,"passed_time":0.2191864066,"remaining_time":1.755465905},
{"learn":[5.188716772],"iteration":111,"passed_time":0.2198409095,"remaining_time":1.743024354},
{"learn":[5.182163132],"iteration":112,"passed_time":0.2205476521,"remaining_time":1.731201481},
{"learn":[5.17764747],"iteration":113,"passed_time":0.2211722274,"remaining_time":1.71893503},
{"learn":[5.170548056],"iteration":114,"passed_time":0.221879541,"remaining_time":1.707507772},
{"learn":[5.165901827],"iteration":115,"passed_time":0.2224872741,"remaining_time":1.695506468},
{"learn":[5.160333668],"iteration":116,"passed_time":0.2233520591,"remaining_time":1.685639899},
{"learn":[5.148953243],"iteration":117,"passed_time":0.2241108663,"remaining_time":1.675133764},
{"learn":[5.144729126],"iteration":118,"passed_time":0.2246070559,"remaining_time":1.662847196},
{"learn":[5.139939946],"iteration":119,"passed_time":0.2252496557,"remaining_time":1.651830809},
{"learn":[5.132898872],"iteration":120,"passed_time":0.2258662357,"remaining_time":1.64079687},
{"learn":[5.129073077],"iteration":121,"passed_time":0.2264746201,"remaining_time":1.629874725},
{"learn":[5.127123916],"iteration":122,"passed_time":0.2268105129,"remaining_time":1.617177397},
{"learn":[5.121282057],"iteration":123,"passed_time":0.2274198791,"remaining_time":1.606611404},
{"learn":[5.114489821],"iteration":124,"passed_time":0.2281503824,"remaining_time":1.597052677},
{"learn":[5.107777291],"iteration":125,"passed_time":0.2288783156,"remaining_time":1.587616252},
{"learn":[5.103518754],"iteration":126,"passed_time":0.2295341507,"remaining_time":1.577821367},
{"learn":[5.101133351],"iteration":127,"passed_time":0.2299317917,"remaining_time":1.566410331},
{"learn":[5.096462705],"iteration":128,"passed_time":0.230535968,"remaining_time":1.556564559},
{"learn":[5.08562082],"iteration":129,"passed_time":0.2311456448,"remaining_time":1.546897776},
{"learn":[5.080483682],"iteration":130,"passed_time":0.2317759711,"remaining_time":1.537506251},
{"learn":[5.07437499],"iteration":131,"passed_time":0.2323909781,"remaining_time":1.528146735},
{"learn":[5.070683732],"iteration":132,"passed_time":0.2329846542,"remaining_time":1.518779663},
{"learn":[5.06432037],"iteration":133,"passed_time":0.2335890109,"remaining_time":1.509612563},
{"learn":[5.057436484],"iteration":134,"passed_time":0.234462878,"remaining_time":1.502299181},
{"learn":[5.053254656],"iteration":135,"passed_time":0.2352288589,"remaining_time":1.494395104},
{"learn":[5.04801663],"iteration":136,"passed_time":0.2358902947,"remaining_time":1.485936674},
{"learn":[5.045680836],"iteration":137,"passed_time":0.2363867749,"remaining_time":1.476560869},
{"learn":[5.041857933],"iteration":138,"passed_time":0.2369991969,"remaining_time":1.468030997},
{"learn":[5.035264888],"iteration":139,"passed_time":0.2376109377,"remaining_time":1.459610046},
{"learn":[5.028771948],"iteration":140,"passed_time":0.2382089021,"remaining_time":1.451215935},
{"learn":[5.024912247],"iteration":141,"passed_time":0.2387934909,"remaining_time":1.442850811},
{"learn":[5.02239068],"iteration":142,"passed_time":0.2393869967,"remaining_time":1.434647945},
{"learn":[5.017110572],"iteration":143,"passed_time":0.2399758937,"remaining_time":1.426523368},
{"learn":[5.010707886],"iteration":144,"passed_time":0.2406938077,"remaining_time":1.419263487},
{"learn":[5.004389868],"iteration":145,"passed_time":0.2414477609,"remaining_time":1.412304026},
{"learn":[4.997628683],"iteration":146,"passed_time":0.2421061206,"remaining_time":1.404874291},
{"learn":[4.991497851],"iteration":147,"passed_time":0.2427157272,"remaining_time":1.397255403},
{"learn":[4.988345253],"iteration":148,"passed_time":0.2433301531,"remaining_time":1.389758123},
{"learn":[4.98460423],"iteration":149,"passed_time":0.2439323456,"remaining_time":1.382283292},
{"learn":[4.982441783],"iteration":150,"passed_time":0.2445473826,"remaining_time":1.374971708},
{"learn":[4.977461771],"iteration":151,"passed_time":0.2451298774,"remaining_time":1.367566684},
{"learn":[4.973601586],"iteration":152,"passed_time":0.2457329616,"remaining_time":1.360364827},
{"learn":[4.968328804],"iteration":153,"passed_time":0.2463327394,"remaining_time":1.353230504},
{"learn":[4.9640736],"iteration":154,"passed_time":0.2471000479,"remaining_time":1.34709381},
{"learn":[4.960865882],"iteration":155,"passed_time":0.2478377193,"remaining_time":1.34086561},
{"learn":[4.957014156],"iteration":156,"passed_time":0.248495919,"remaining_time":1.334280635},
{"learn":[4.952244852],"iteration":157,"passed_time":0.2491181098,"remaining_time":1.327578787},
{"learn":[4.949695675],"iteration":158,"passed_time":0.2497042615,"remaining_time":1.320762792},
{"learn":[4.946584698],"iteration":159,"passed_time":0.2503056224,"remaining_time":1.314104518},
{"learn":[4.940192834],"iteration":160,"passed_time":0.2509049193,"remaining_time":1.307510729},
{"learn":[4.936727994],"iteration":161,"passed_time":0.2514860515,"remaining_time":1.300896982},
{"learn":[4.932342063],"iteration":162,"passed_time":0.2520943056,"remaining_time":1.294496526},
{"learn":[4.925830838],"iteration":163,"passed_time":0.2527118174,"remaining_time":1.288213898},
{"learn":[4.922571773],"iteration":164,"passed_time":0.2534657155,"remaining_time":1.282690136},
{"learn":[4.918395814],"iteration":165,"passed_time":0.2541875065,"remaining_time":1.277062533},
{"learn":[4.911142452],"iteration":166,"passed_time":0.2549094044,"remaining_time":1.271494215},
{"learn":[4.908276131],"iteration":167,"passed_time":0.2555203335,"remaining_time":1.265434033},
{"learn":[4.904584645],"iteration":168,"passed_time":0.2561487863,"remaining_time":1.259524505},
{"learn":[4.89795517],"iteration":169,"passed_time":0.2567628114,"remaining_time":1.253606667},
{"learn":[4.895556491],"iteration":170,"passed_time":0.2573808943,"remaining_time":1.247770534},
{"learn":[4.890591233],"iteration":171,"passed_time":0.2579786883,"remaining_time":1.241897407},
{"learn":[4.884629277],"iteration":172,"passed_time":0.2585917015,"remaining_time":1.236158018},
{"learn":[4.880550786],"iteration":173,"passed_time":0.2593704719,"remaining_time":1.231264424},
{"learn":[4.876384842],"iteration":174,"passed_time":0.2600830995,"remaining_time":1.22610604},
{"learn":[4.872638238],"iteration":175,"passed_time":0.2607880887,"remaining_time":1.220962415},
{"learn":[4.869137118],"iteration":176,"passed_time":0.261456548,"remaining_time":1.21569909},
{"learn":[4.863587157],"iteration":177,"passed_time":0.2621430117,"remaining_time":1.210570537},
{"learn":[4.858028614],"iteration":178,"passed_time":0.2628377413,"remaining_time":1.205529529},
{"learn":[4.853838176],"iteration":179,"passed_time":0.2634951695,"remaining_time":1.200366883},
{"learn":[4.853462329],"iteration":180,"passed_time":0.2638649873,"remaining_time":1.193952622},
{"learn":[4.851573196],"iteration":181,"passed_time":0.2645113743,"remaining_time":1.188847825},
{"learn":[4.848442087],"iteration":182,"passed_time":0.2651763472,"remaining_time":1.183874731},
{"learn":[4.845547104],"iteration":183,"passed_time":0.2659267233,"remaining_time":1.179327208},
{"learn":[4.839868817],"iteration":184,"passed_time":0.2666019753,"remaining_time":1.174489783},
{"learn":[4.836336958],"iteration":185,"passed_time":0.2673370821,"remaining_time":1.169959058},
{"learn":[4.831124789],"iteration":186,"passed_time":0.2680409893,"remaining_time":1.165333285},
{"learn":[4.827407333],"iteration":187,"passed_time":0.2687211209,"remaining_time":1.160646543},
{"learn":[4.824088918],"iteration":188,"passed_time":0.2694548351,"remaining_time":1.156232123},
{"learn":[4.820934539],"iteration":189,"passed_time":0.2702519105,"remaining_time":1.152126566},
{"learn":[4.816975227],"iteration":190,"passed_time":0.2708850823,"remaining_time":1.147361422},
{"learn":[4.812340486],"iteration":191,"passed_time":0.2715398557,"remaining_time":1.142730226},
{"learn":[4.806402747],"iteration":192,"passed_time":0.2721601829,"remaining_time":1.137996205},
{"learn":[4.801521788],"iteration":193,"passed_time":0.2728028425,"remaining_time":1.133397376},
{"learn":[4.797601172],"iteration":194,"passed_time":0.2734733159,"remaining_time":1.128953945},
{"learn":[4.792694629],"iteration":195,"passed_time":0.274166733,"remaining_time":1.124643129},
{"learn":[4.789794613],"iteration":196,"passed_time":0.2748169571,"remaining_time":1.120192977},
{"learn":[4.785367055],"iteration":197,"passed_time":0.2755197273,"remaining_time":1.115994047},
{"learn":[4.780376856],"iteration":198,"passed_time":0.276308712,"remaining_time":1.112177278},
{"learn":[4.776691261],"iteration":199,"passed_time":0.2771251495,"remaining_time":1.108500598},
{"learn":[4.773470753],"iteration":200,"passed_time":0.2777752991,"remaining_time":1.104191363},
{"learn":[4.77207327],"iteration":201,"passed_time":0.2784786194,"remaining_time":1.100128407},
{"learn":[4.767347177],"iteration":202,"passed_time":0.2792050747,"remaining_time":1.096189382},
{"learn":[4.763983068],"iteration":203,"passed_time":0.2799244518,"remaining_time":1.092254233},
{"learn":[4.761588849],"iteration":204,"passed_time":0.2805948348,"remaining_time":1.088160457},
{"learn":[4.758558086],"iteration":205,"passed_time":0.2812737841,"remaining_time":1.084132935},
{"learn":[4.753678804],"iteration":206,"passed_time":0.2819564105,"remaining_time":1.080151853},
{"learn":[4.746510889],"iteration":207,"passed_time":0.282592568,"remaining_time":1.076025547},
{"learn":[4.744840601],"iteration":208,"passed_time":0.283259324,"remaining_time":1.072048446},
{"learn":[4.741702222],"iteration":209,"passed_time":0.2839136363,"remaining_time":1.06805606},
{"learn":[4.739352853],"iteration":210,"passed_time":0.2845676482,"remaining_time":1.064094192},
{"learn":[4.735539287],"iteration":211,"passed_time":0.2853198979,"remaining_time":1.060528677},
{"learn":[4.730726751],"iteration":212,"passed_time":0.2859359168,"remaining_time":1.056486228},
{"learn":[4.726416092],"iteration":213,"passed_time":0.2866366338,"remaining_time":1.052786889},
{"learn":[4.721293082],"iteration":214,"passed_time":0.2872417118,"remaining_time":1.04876625},
{"learn":[4.718443695],"iteration":215,"passed_time":0.2878369008,"remaining_time":1.044741344},
{"learn":[4.711627962],"iteration":216,"passed_time":0.2884453152,"remaining_time":1.040795769},
{"learn":[4.709790764],"iteration":217,"passed_time":0.2890551022,"remaining_time":1.036885734},
{"learn":[4.706913073],"iteration":218,"passed_time":0.2896416447,"remaining_time":1.032922943},
{"learn":[4.703846389],"iteration":219,"passed_time":0.2902440376,"remaining_time":1.029047042},
{"learn":[4.701001135],"iteration":220,"passed_time":0.2912003515,"remaining_time":1.026448298},
{"learn":[4.700380864],"iteration":221,"passed_time":0.2918707643,"remaining_time":1.022862408},
{"learn":[4.695837486],"iteration":222,"passed_time":0.292559158,"remaining_time":1.019365317},
{"learn":[4.691242996],"iteration":223,"passed_time":0.2932604172,"remaining_time":1.015937874},
{"learn":[4.690284609],"iteration":224,"passed_time":0.2938906934,"remaining_time":1.012290166},
{"learn":[4.68827119],"iteration":225,"passed_time":0.2945082653,"remaining_time":1.008625652},
{"learn":[4.686922425],"iteration":226,"passed_time":0.2950953188,"remaining_time":1.004884059},
{"learn":[4.686085874],"iteration":227,"passed_time":0.2956958682,"remaining_time":1.001215834},
{"learn":[4.683230741],"iteration":228,"passed_time":0.2962822704,"remaining_time":0.9975267707},
{"learn":[4.6773487],"iteration":229,"passed_time":0.2968938408,"remaining_time":0.9939489454},
{"learn":[4.671462906],"iteration":230,"passed_time":0.2975786113,"remaining_time":0.9906404854},
{"learn":[4.664799601],"iteration":231,"passed_time":0.2982062124,"remaining_time":0.9871653929},
{"learn":[4.660979386],"iteration":232,"passed_time":0.2988227424,"remaining_time":0.9836782978},
{"learn":[4.656281279],"iteration":233,"passed_time":0.2994439111,"remaining_time":0.9802309228},
{"learn":[4.651997094],"iteration":234,"passed_time":0.3000491695,"remaining_time":0.976755807},
{"learn":[4.650151977],"iteration":235,"passed_time":0.3006337983,"remaining_time":0.9732382285},
{"learn":[4.648478046],"iteration":236,"passed_time":0.3012289373,"remaining_time":0.969779237},
{"learn":[4.646364602],"iteration":237,"passed_time":0.301835919,"remaining_time":0.9663822279},
{"learn":[4.642635873],"iteration":238,"passed_time":0.3024229224,"remaining_time":0.9629449536},
{"learn":[4.640860821],"iteration":239,"passed_time":0.302993324,"remaining_time":0.9594788593},
{"learn":[4.639446822],"iteration":240,"passed_time":0.3037189959,"remaining_time":0.9565258004},
{"learn":[4.637120072],"iteration":241,"passed_time":0.3043455444,"remaining_time":0.953280672},
{"learn":[4.633769267],"iteration":242,"passed_time":0.3049735863,"remaining_time":0.9500617483},
{"learn":[4.630491517],"iteration":243,"passed_time":0.3055901162,"remaining_time":0.9468283929},
{"learn":[4.627813333],"iteration":244,"passed_time":0.3061983803,"remaining_time":0.9435909271},
{"learn":[4.622496304],"iteration":245,"passed_time":0.306808508,"remaining_time":0.9403805488},
{"learn":[4.618979301],"iteration":246,"passed_time":0.307500002,"remaining_time":0.9374392773},
{"learn":[4.616563458],"iteration":247,"passed_time":0.3081410288,"remaining_time":0.9343631195},
{"learn":[4.614759385],"iteration":248,"passed_time":0.3087374502,"remaining_time":0.9311719884},
{"learn":[4.61251363],"iteration":249,"passed_time":0.3093463856,"remaining_time":0.9280391567},
{"learn":[4.608796693],"iteration":250,"passed_time":0.310053135,"remaining_time":0.9252183193},
{"learn":[4.60847774],"iteration":251,"passed_time":0.3106688308,"remaining_time":0.92214399},
{"learn":[4.605195659],"iteration":252,"passed_time":0.3113784492,"remaining_time":0.9193664093},
{"learn":[4.60103766],"iteration":253,"passed_time":0.3120008003,"remaining_time":0.9163488071},
{"learn":[4.599325598],"iteration":254,"passed_time":0.3126052571,"remaining_time":0.9132977118},
{"learn":[4.597012808],"iteration":255,"passed_time":0.3132237908,"remaining_time":0.9103066421},
{"learn":[4.594161533],"iteration":256,"passed_time":0.3138581248,"remaining_time":0.9073797149},
{"learn":[4.592197259],"iteration":257,"passed_time":0.3144445772,"remaining_time":0.9043328537},
{"learn":[4.58952828],"iteration":258,"passed_time":0.3150583318,"remaining_time":0.9013831036},
{"learn":[4.585816572],"iteration":259,"passed_time":0.3156494029,"remaining_time":0.8983867622},
{"learn":[4.582934052],"iteration":260,"passed_time":0.3163792798,"remaining_time":0.8958018688},
{"learn":[4.582234842],"iteration":261,"passed_time":0.3170186935,"remaining_time":0.8929763198},
{"learn":[4.57571562],"iteration":262,"passed_time":0.3176844576,"remaining_time":0.8902412368},
{"learn":[4.571197349],"iteration":263,"passed_time":0.3183088726,"remaining_time":0.887406554},
{"learn":[4.56723703],"iteration":264,"passed_time":0.3188979199,"remaining_time":0.8844904572},
{"learn":[4.560335567],"iteration":265,"passed_time":0.3195056831,"remaining_time":0.8816435014},
{"learn":[4.554709345],"iteration":266,"passed_time":0.3200931173,"remaining_time":0.8787575093},
{"learn":[4.552806306],"iteration":267,"passed_time":0.3206892382,"remaining_time":0.8759123968},
{"learn":[4.550766241],"iteration":268,"passed_time":0.3213879654,"remaining_time":0.8733628353},
{"learn":[4.549216045],"iteration":269,"passed_time":0.3219983535,"remaining_time":0.870588141},
{"learn":[4.547687452],"iteration":270,"passed_time":0.3227044646,"remaining_time":0.8680869176},
{"learn":[4.545642435],"iteration":271,"passed_time":0.3233548195,"remaining_time":0.8654496641},
{"learn":[4.543930359],"iteration":272,"passed_time":0.3239842541,"remaining_time":0.8627712555},
{"learn":[4.541029943],"iteration":273,"passed_time":0.3246261025,"remaining_time":0.860140695},
{"learn":[4.537781449],"iteration":274,"passed_time":0.3252349778,"remaining_time":0.8574376687},
{"learn":[4.53066128],"iteration":275,"passed_time":0.3258376912,"remaining_time":0.8547336538},
{"learn":[4.526763956],"iteration":276,"passed_time":0.326449973,"remaining_time":0.8520697852},
{"learn":[4.522036004],"iteration":277,"passed_time":0.3270518749,"remaining_time":0.8493937184},
{"learn":[4.515307629],"iteration":278,"passed_time":0.3276613714,"remaining_time":0.8467521461},
{"learn":[4.51109143],"iteration":279,"passed_time":0.328275667,"remaining_time":0.8441374295},
{"learn":[4.508233494],"iteration":280,"passed_time":0.3290156732,"remaining_time":0.8418586088},
{"learn":[4.502555629],"iteration":281,"passed_time":0.3296372228,"remaining_time":0.8392890991},
{"learn":[4.500081355],"iteration":282,"passed_time":0.3302601549,"remaining_time":0.836736859},
{"learn":[4.495281743],"iteration":283,"passed_time":0.3308893491,"remaining_time":0.8342139928},
{"learn":[4.492138869],"iteration":284,"passed_time":0.3314935855,"remaining_time":0.8316418021},
{"learn":[4.491708261],"iteration":285,"passed_time":0.3320875722,"remaining_time":0.8290577852},
{"learn":[4.489398865],"iteration":286,"passed_time":0.3326852962,"remaining_time":0.8264969204},
{"learn":[4.485796373],"iteration":287,"passed_time":0.3333067355,"remaining_time":0.8240083182},
{"learn":[4.479542205],"iteration":288,"passed_time":0.3339068439,"remaining_time":0.8214801593},
{"learn":[4.475986993],"iteration":289,"passed_time":0.3345138657,"remaining_time":0.8189822228},
{"learn":[4.468661855],"iteration":290,"passed_time":0.3351967025,"remaining_time":0.8166820002},
{"learn":[4.463785664],"iteration":291,"passed_time":0.336102346,"remaining_time":0.8149330855},
{"learn":[4.460445831],"iteration":292,"passed_time":0.3368163825,"remaining_time":0.8127275851},
{"learn":[4.45692492],"iteration":293,"passed_time":0.3375418005,"remaining_time":0.8105595618},
{"learn":[4.454031688],"iteration":294,"passed_time":0.3381969443,"remaining_time":0.8082333754},
{"learn":[4.451672391],"iteration":295,"passed_time":0.3388909929,"remaining_time":0.8060110101},
{"learn":[4.45031553],"iteration":296,"passed_time":0.3395475895,"remaining_time":0.8037102876},
{"learn":[4.446782666],"iteration":297,"passed_time":0.3402251662,"remaining_time":0.8014700225},
{"learn":[4.444369689],"iteration":298,"passed_time":0.340898565,"remaining_time":0.7992304149},
{"learn":[4.44411683],"iteration":299,"passed_time":0.3415955689,"remaining_time":0.7970563274},
{"learn":[4.440876943],"iteration":300,"passed_time":0.3423368175,"remaining_time":0.7949948021},
{"learn":[4.439336453],"iteration":301,"passed_time":0.3430502629,"remaining_time":0.7928777599},
{"learn":[4.436666901],"iteration":302,"passed_time":0.3437503928,"remaining_time":0.7907393524},
{"learn":[4.433043336],"iteration":303,"passed_time":0.3445313837,"remaining_time":0.7887955364},
{"learn":[4.431419305],"iteration":304,"passed_time":0.3455041294,"remaining_time":0.7872962949},
{"learn":[4.428859646],"iteration":305,"passed_time":0.3461614871,"remaining_time":0.7850852028},
{"learn":[4.424552441],"iteration":306,"passed_time":0.3468658514,"remaining_time":0.7829903421},
{"learn":[4.422706391],"iteration":307,"passed_time":0.3478597376,"remaining_time":0.7815549948},
{"learn":[4.421427994],"iteration":308,"passed_time":0.3485039404,"remaining_time":0.779340527},
{"learn":[4.418733158],"iteration":309,"passed_time":0.3491740028,"remaining_time":0.7771937481},
{"learn":[4.415656941],"iteration":310,"passed_time":0.349795392,"remaining_time":0.7749486337},
{"learn":[4.410747417],"iteration":311,"passed_time":0.3504139157,"remaining_time":0.772707609},
{"learn":[4.408126521],"iteration":312,"passed_time":0.351016028,"remaining_time":0.7704409306},
{"learn":[4.407843853],"iteration":313,"passed_time":0.3516005166,"remaining_time":0.7681463516},
{"learn":[4.405219398],"iteration":314,"passed_time":0.3522242303,"remaining_time":0.7659479294},
{"learn":[4.402708465],"iteration":315,"passed_time":0.3528246694,"remaining_time":0.7637090946},
{"learn":[4.40104971],"iteration":316,"passed_time":0.3534464293,"remaining_time":0.7615265339},
{"learn":[4.400830038],"iteration":317,"passed_time":0.3541535025,"remaining_time":0.759536757},
{"learn":[4.39784288],"iteration":318,"passed_time":0.3548428618,"remaining_time":0.7575172066},
{"learn":[4.393741845],"iteration":319,"passed_time":0.3554822151,"remaining_time":0.7553997071},
{"learn":[4.393425936],"iteration":320,"passed_time":0.3560715329,"remaining_time":0.753185579},
{"learn":[4.390505974],"iteration":321,"passed_time":0.3566743165,"remaining_time":0.7510098963},
{"learn":[4.390305136],"iteration":322,"passed_time":0.3572670108,"remaining_time":0.748822806},
{"learn":[4.38568203],"iteration":323,"passed_time":0.3578661575,"remaining_time":0.7466590199},
{"learn":[4.383057135],"iteration":324,"passed_time":0.3584654043,"remaining_time":0.7445050705},
{"learn":[4.380662684],"iteration":325,"passed_time":0.3590658134,"remaining_time":0.742363062},
{"learn":[4.37805727],"iteration":326,"passed_time":0.3596561732,"remaining_time":0.7402097999},
{"learn":[4.373708319],"iteration":327,"passed_time":0.3603869518,"remaining_time":0.7383537548},
{"learn":[4.36887921],"iteration":328,"passed_time":0.3611767934,"remaining_time":0.7366250102},
{"learn":[4.367895929],"iteration":329,"passed_time":0.3620305711,"remaining_time":0.7350317655},
{"learn":[4.362140573],"iteration":330,"passed_time":0.3627811375,"remaining_time":0.7332343836},
{"learn":[4.361931924],"iteration":331,"passed_time":0.3634257612,"remaining_time":0.731230146},
{"learn":[4.359656377],"iteration":332,"passed_time":0.3640406379,"remaining_time":0.729174491},
{"learn":[4.354281355],"iteration":333,"passed_time":0.3646511263,"remaining_time":0.7271187129},
{"learn":[4.348589447],"iteration":334,"passed_time":0.3652526374,"remaining_time":0.725053743},
{"learn":[4.346355698],"iteration":335,"passed_time":0.3658673038,"remaining_time":0.7230234813},
{"learn":[4.343894047],"iteration":336,"passed_time":0.3666807405,"remaining_time":0.7213926735},
{"learn":[4.341561356],"iteration":337,"passed_time":0.3673687172,"remaining_time":0.7195209786},
{"learn":[4.338869061],"iteration":338,"passed_time":0.3680431078,"remaining_time":0.7176297766},
{"learn":[4.333720063],"iteration":339,"passed_time":0.3686635051,"remaining_time":0.7156409217},
{"learn":[4.330892223],"iteration":340,"passed_time":0.3692744544,"remaining_time":0.7136418341},
{"learn":[4.328311474],"iteration":341,"passed_time":0.3698729798,"remaining_time":0.7116269612},
{"learn":[4.324580133],"iteration":342,"passed_time":0.3704771461,"remaining_time":0.7096311515},
{"learn":[4.323354432],"iteration":343,"passed_time":0.3710996174,"remaining_time":0.7076783401},
{"learn":[4.323159553],"iteration":344,"passed_time":0.371669508,"remaining_time":0.7056334138},
{"learn":[4.318639682],"iteration":345,"passed_time":0.37227666,"remaining_time":0.703667444},
{"learn":[4.312712208],"iteration":346,"passed_time":0.3730263046,"remaining_time":0.7019774551},
{"learn":[4.311461062],"iteration":347,"passed_time":0.3736757375,"remaining_time":0.7001051174},
{"learn":[4.311178356],"iteration":348,"passed_time":0.3743225454,"remaining_time":0.6982348912},
{"learn":[4.311102505],"iteration":349,"passed_time":0.3749157206,"remaining_time":0.6962720525},
{"learn":[4.310232308],"iteration":350,"passed_time":0.3755200171,"remaining_time":0.6943375815},
{"learn":[4.305128197],"iteration":351,"passed_time":0.3761216585,"remaining_time":0.6924057804},
{"learn":[4.304595496],"iteration":352,"passed_time":0.3768217386,"remaining_time":0.6906619402},
{"learn":[4.3004992],"iteration":353,"passed_time":0.3774408936,"remaining_time":0.6887763199},
{"learn":[4.297581524],"iteration":354,"passed_time":0.3780508609,"remaining_time":0.6868811417},
{"learn":[4.297355825],"iteration":355,"passed_time":0.378672841,"remaining_time":0.6850149145},
{"learn":[4.295758715],"iteration":356,"passed_time":0.3793247486,"remaining_time":0.6832095612},
{"learn":[4.292500657],"iteration":357,"passed_time":0.3799987384,"remaining_time":0.6814502516},
{"learn":[4.290797586],"iteration":358,"passed_time":0.3806553851,"remaining_time":0.6796660219},
{"learn":[4.286410608],"iteration":359,"passed_time":0.3812777061,"remaining_time":0.6778270331},
{"learn":[4.280278245],"iteration":360,"passed_time":0.3818976025,"remaining_time":0.675990493},
{"learn":[4.279941283],"iteration":361,"passed_time":0.382478404,"remaining_time":0.6740917728},
{"learn":[4.274426275],"iteration":362,"passed_time":0.3830685935,"remaining_time":0.6722167881},
{"learn":[4.273567658],"iteration":363,"passed_time":0.3836567892,"remaining_time":0.6703453789},
{"learn":[4.269488271],"iteration":364,"passed_time":0.3842734594,"remaining_time":0.6685305389},
{"learn":[4.266838205],"iteration":365,"passed_time":0.3849234236,"remaining_time":0.6667799196},
{"learn":[4.263456509],"iteration":366,"passed_time":0.3855925943,"remaining_time":0.6650684255},
{"learn":[4.260360204],"iteration":367,"passed_time":0.3862495713,"remaining_time":0.663341655},
{"learn":[4.255120549],"iteration":368,"passed_time":0.3869481181,"remaining_time":0.6616917684},
{"learn":[4.252582211],"iteration":369,"passed_time":0.3875631151,"remaining_time":0.6599047636},
{"learn":[4.247857931],"iteration":370,"passed_time":0.38819794,"remaining_time":0.6581576935},
{"learn":[4.245288911],"iteration":371,"passed_time":0.388795173,"remaining_time":0.6563531416},
{"learn":[4.24048515],"iteration":372,"passed_time":0.3894137869,"remaining_time":0.6545910038},
{"learn":[4.2378365],"iteration":373,"passed_time":0.3900036859,"remaining_time":0.6527869181},
{"learn":[4.236751063],"iteration":374,"passed_time":0.3906306257,"remaining_time":0.6510510428},
{"learn":[4.233240093],"iteration":375,"passed_time":0.3913423528,"remaining_time":0.649461777},
{"learn":[4.230358421],"iteration":376,"passed_time":0.3920699553,"remaining_time":0.6479034009},
{"learn":[4.225853583],"iteration":377,"passed_time":0.3927237565,"remaining_time":0.6462279803},
{"learn":[4.224702126],"iteration":378,"passed_time":0.393355726,"remaining_time":0.644522179},
{"learn":[4.224361982],"iteration":379,"passed_time":0.3939509852,"remaining_time":0.6427621337},
{"learn":[4.223787954],"iteration":380,"passed_time":0.3945707814,"remaining_time":0.6410480673},
{"learn":[4.22144054],"iteration":381,"passed_time":0.3951778832,"remaining_time":0.6393191933},
{"learn":[4.217739335],"iteration":382,"passed_time":0.3958048331,"remaining_time":0.6376281515},
{"learn":[4.215611665],"iteration":383,"passed_time":0.3963970965,"remaining_time":0.635887009},
{"learn":[4.210236863],"iteration":384,"passed_time":0.3969958725,"remaining_time":0.6341622379},
{"learn":[4.208454294],"iteration":385,"passed_time":0.39766081,"remaining_time":0.6325485424},
{"learn":[4.207446501],"iteration":386,"passed_time":0.3983653584,"remaining_time":0.6310024928},
{"learn":[4.204985442],"iteration":387,"passed_time":0.3991489978,"remaining_time":0.6295855326},
{"learn":[4.202796622],"iteration":388,"passed_time":0.3997864578,"remaining_time":0.6279422255},
{"learn":[4.199774004],"iteration":389,"passed_time":0.4003998417,"remaining_time":0.626266419},
{"learn":[4.199458358],"iteration":390,"passed_time":0.4009794209,"remaining_time":0.6245433946},
{"learn":[4.19751254],"iteration":391,"passed_time":0.4015808819,"remaining_time":0.6228601434},
{"learn":[4.195201346],"iteration":392,"passed_time":0.402178135,"remaining_time":0.621175898},
{"learn":[4.190593508],"iteration":393,"passed_time":0.4027813293,"remaining_time":0.6195063086},
{"learn":[4.187212054],"iteration":394,"passed_time":0.4033811974,"remaining_time":0.6178370238},
{"learn":[4.184984466],"iteration":395,"passed_time":0.4040744294,"remaining_time":0.6163155438},
{"learn":[4.182832144],"iteration":396,"passed_time":0.4047854548,"remaining_time":0.6148252626},
{"learn":[4.179752812],"iteration":397,"passed_time":0.4055330957,"remaining_time":0.6133942804},
{"learn":[4.17878934],"iteration":398,"passed_time":0.4061873331,"remaining_time":0.611826033},
{"learn":[4.174548229],"iteration":399,"passed_time":0.4068612725,"remaining_time":0.6102919088},
{"learn":[4.168872556],"iteration":400,"passed_time":0.4075160106,"remaining_time":0.6087333923},
{"learn":[4.163926494],"iteration":401,"passed_time":0.4081930162,"remaining_time":0.6072124967},
{"learn":[4.159485076],"iteration":402,"passed_time":0.4088836129,"remaining_time":0.6057159228},
{"learn":[4.155926102],"iteration":403,"passed_time":0.4095390626,"remaining_time":0.6041714884},
{"learn":[4.153540115],"iteration":404,"passed_time":0.4102127068,"remaining_time":0.6026581742},
{"learn":[4.150983044],"iteration":405,"passed_time":0.4109612293,"remaining_time":0.6012585473},
{"learn":[4.146539132],"iteration":406,"passed_time":0.4117646416,"remaining_time":0.5999420945},
{"learn":[4.144869174],"iteration":407,"passed_time":0.412372565,"remaining_time":0.5983445061},
{"learn":[4.142825962],"iteration":408,"passed_time":0.4129744268,"remaining_time":0.5967429982},
{"learn":[4.142467378],"iteration":409,"passed_time":0.4135778316,"remaining_time":0.595148587},
{"learn":[4.141800768],"iteration":410,"passed_time":0.4141658069,"remaining_time":0.5935368863},
{"learn":[4.140107084],"iteration":411,"passed_time":0.4147569382,"remaining_time":0.5919346594},
{"learn":[4.136243196],"iteration":412,"passed_time":0.4153651923,"remaining_time":0.5903616655},
{"learn":[4.133618439],"iteration":413,"passed_time":0.4159722841,"remaining_time":0.5887916872},
{"learn":[4.131053025],"iteration":414,"passed_time":0.4166419861,"remaining_time":0.5873146069},
{"learn":[4.128379975],"iteration":415,"passed_time":0.4173171329,"remaining_time":0.5858490519},
{"learn":[4.127068571],"iteration":416,"passed_time":0.4179743908,"remaining_time":0.5843622777},
{"learn":[4.125969877],"iteration":417,"passed_time":0.4185619051,"remaining_time":0.5827823655},
{"learn":[4.123893633],"iteration":418,"passed_time":0.4191654602,"remaining_time":0.5812294329},
{"learn":[4.119643722],"iteration":419,"passed_time":0.4200574172,"remaining_time":0.5800792905},
{"learn":[4.11465686],"iteration":420,"passed_time":0.4207490008,"remaining_time":0.5786548016},
{"learn":[4.111565986],"iteration":421,"passed_time":0.4213586475,"remaining_time":0.5771215599},
{"learn":[4.106322452],"iteration":422,"passed_time":0.4219652084,"remaining_time":0.5755884757},
{"learn":[4.104222175],"iteration":423,"passed_time":0.4225843433,"remaining_time":0.5740768437},
{"learn":[4.103008002],"iteration":424,"passed_time":0.4232559486,"remaining_time":0.572640401},
{"learn":[4.099176337],"iteration":425,"passed_time":0.4240303728,"remaining_time":0.5713460892},
{"learn":[4.096525716],"iteration":426,"passed_time":0.424716536,"remaining_time":0.5699357732},
{"learn":[4.094967724],"iteration":427,"passed_time":0.4253629832,"remaining_time":0.5684757626},
{"learn":[4.094683584],"iteration":428,"passed_time":0.4259658469,"remaining_time":0.5669615352},
{"learn":[4.091096563],"iteration":429,"passed_time":0.4265511471,"remaining_time":0.5654282648},
{"learn":[4.089178677],"iteration":430,"passed_time":0.4272092967,"remaining_time":0.563995568},
{"learn":[4.085335077],"iteration":431,"passed_time":0.4278510348,"remaining_time":0.5625448791},
{"learn":[4.084852122],"iteration":432,"passed_time":0.4284621343,"remaining_time":0.5610578064},
{"learn":[4.080322952],"iteration":433,"passed_time":0.429083263,"remaining_time":0.55958785},
{"learn":[4.077449519],"iteration":434,"passed_time":0.4297398596,"remaining_time":0.5581678637},
{"learn":[4.076568374],"iteration":435,"passed_time":0.430468434,"remaining_time":0.556844488},
{"learn":[4.076071793],"iteration":436,"passed_time":0.4311572701,"remaining_time":0.5554726386},
{"learn":[4.075027644],"iteration":437,"passed_time":0.4318983884,"remaining_time":0.5541709915},
{"learn":[4.07020837],"iteration":438,"passed_time":0.432562279,"remaining_time":0.5527732084},
{"learn":[4.06833694],"iteration":439,"passed_time":0.4331997289,"remaining_time":0.5513451095},
{"learn":[4.063936568],"iteration":440,"passed_time":0.4339892098,"remaining_time":0.5501133068},
{"learn":[4.061734926],"iteration":441,"passed_time":0.4346812543,"remaining_time":0.5487604975},
{"learn":[4.060815619],"iteration":442,"passed_time":0.4353431313,"remaining_time":0.5473727407},
{"learn":[4.056407489],"iteration":443,"passed_time":0.4360622272,"remaining_time":0.5460599061},
{"learn":[4.05238936],"iteration":444,"passed_time":0.4368197272,"remaining_time":0.5447976373},
{"learn":[4.049685254],"iteration":445,"passed_time":0.4374588503,"remaining_time":0.5433905899},
{"learn":[4.045162016],"iteration":446,"passed_time":0.4380931943,"remaining_time":0.5419810659},
{"learn":[4.042955482],"iteration":447,"passed_time":0.4386961583,"remaining_time":0.5405363379},
{"learn":[4.041467663],"iteration":448,"passed_time":0.4392893435,"remaining_time":0.5390833592},
{"learn":[4.038920476],"iteration":449,"passed_time":0.4399086988,"remaining_time":0.5376661875},
{"learn":[4.036694383],"iteration":450,"passed_time":0.4405101298,"remaining_time":0.5362307346},
{"learn":[4.034999007],"iteration":451,"passed_time":0.4411207084,"remaining_time":0.5348100624},
{"learn":[4.031928018],"iteration":452,"passed_time":0.4417120501,"remaining_time":0.5333697382},
{"learn":[4.028718143],"iteration":453,"passed_time":0.4425504947,"remaining_time":0.5322303306},
{"learn":[4.027401978],"iteration":454,"passed_time":0.4432259674,"remaining_time":0.5308970379},
{"learn":[4.025930598],"iteration":455,"passed_time":0.4438909601,"remaining_time":0.5295541278},
{"learn":[4.021074523],"iteration":456,"passed_time":0.4445001359,"remaining_time":0.5281478639},
{"learn":[4.020268486],"iteration":457,"passed_time":0.4450969681,"remaining_time":0.5267304732},
{"learn":[4.017986361],"iteration":458,"passed_time":0.4456851237,"remaining_time":0.5253064312},
{"learn":[4.014814804],"iteration":459,"passed_time":0.4462790504,"remaining_time":0.5238927983},
{"learn":[4.009704796],"iteration":460,"passed_time":0.4468819242,"remaining_time":0.5224931825},
{"learn":[4.008440457],"iteration":461,"passed_time":0.4474866114,"remaining_time":0.5210991276},
{"learn":[4.004854849],"iteration":462,"passed_time":0.4481509732,"remaining_time":0.5197776946},
{"learn":[4.000898028],"iteration":463,"passed_time":0.449005801,"remaining_time":0.518679115},
{"learn":[3.996617985],"iteration":464,"passed_time":0.4496516971,"remaining_time":0.5173411999},
{"learn":[3.995443319],"iteration":465,"passed_time":0.4502663935,"remaining_time":0.5159705025},
{"learn":[3.990771995],"iteration":466,"passed_time":0.4508934836,"remaining_time":0.514617188},
{"learn":[3.989249359],"iteration":467,"passed_time":0.4514956661,"remaining_time":0.5132386632},
{"learn":[3.986599538],"iteration":468,"passed_time":0.4520931896,"remaining_time":0.5118581742},
{"learn":[3.985628919],"iteration":469,"passed_time":0.4527102405,"remaining_time":0.5105030372},
{"learn":[3.985086112],"iteration":470,"passed_time":0.4533159598,"remaining_time":0.5091383073},
{"learn":[3.98466839],"iteration":471,"passed_time":0.4539089045,"remaining_time":0.5077625034},
{"learn":[3.984233894],"iteration":472,"passed_time":0.4545563064,"remaining_time":0.5064506838},
{"learn":[3.981855845],"iteration":473,"passed_time":0.4552532098,"remaining_time":0.5051965999},
{"learn":[3.978684264],"iteration":474,"passed_time":0.4558908601,"remaining_time":0.5038793717},
{"learn":[3.974361269],"iteration":475,"passed_time":0.45656206,"remaining_time":0.5026019315},
{"learn":[3.972074049],"iteration":476,"passed_time":0.4571941597,"remaining_time":0.5012841625},
{"learn":[3.97191982],"iteration":477,"passed_time":0.4577844093,"remaining_time":0.4999235599},
{"learn":[3.969616848],"iteration":478,"passed_time":0.4583760415,"remaining_time":0.4985676778},
{"learn":[3.968533527],"iteration":479,"passed_time":0.4589611613,"remaining_time":0.4972079248},
{"learn":[3.967568753],"iteration":480,"passed_time":0.4595464515,"remaining_time":0.4958515765},
{"learn":[3.966232553],"iteration":481,"passed_time":0.4601468906,"remaining_time":0.4945147081},
{"learn":[3.961522393],"iteration":482,"passed_time":0.460842602,"remaining_time":0.493282868},
{"learn":[3.955829553],"iteration":483,"passed_time":0.4616356197,"remaining_time":0.492156983},
{"learn":[3.954248095],"iteration":484,"passed_time":0.4622639422,"remaining_time":0.4908575881},
{"learn":[3.951922606],"iteration":485,"passed_time":0.4629179836,"remaining_time":0.4895881555},
{"learn":[3.94978202],"iteration":486,"passed_time":0.4635218192,"remaining_time":0.488268364},
{"learn":[3.949518999],"iteration":487,"passed_time":0.4641233805,"remaining_time":0.4869491205},
{"learn":[3.945431216],"iteration":488,"passed_time":0.4647188,"remaining_time":0.4856263942},
{"learn":[3.943249086],"iteration":489,"passed_time":0.4653314324,"remaining_time":0.4843245521},
{"learn":[3.941981548],"iteration":490,"passed_time":0.4659249483,"remaining_time":0.4830057},
{"learn":[3.936600517],"iteration":491,"passed_time":0.4665392439,"remaining_time":0.4817112519},
{"learn":[3.934476885],"iteration":492,"passed_time":0.4672209689,"remaining_time":0.4804889072},
{"learn":[3.93045798],"iteration":493,"passed_time":0.4680018834,"remaining_time":0.4793703502},
{"learn":[3.925977375],"iteration":494,"passed_time":0.4686433915,"remaining_time":0.4781109347},
{"learn":[3.92457993],"iteration":495,"passed_time":0.4693031037,"remaining_time":0.4768725086},
{"learn":[3.919849146],"iteration":496,"passed_time":0.4699096245,"remaining_time":0.4755825777},
{"learn":[3.919681964],"iteration":497,"passed_time":0.4705005053,"remaining_time":0.4742796258},
{"learn":[3.917633027],"iteration":498,"passed_time":0.4711093204,"remaining_time":0.4729975341},
{"learn":[3.916616419],"iteration":499,"passed_time":0.4716962337,"remaining_time":0.4716962337},
{"learn":[3.912896166],"iteration":500,"passed_time":0.4722829665,"remaining_time":0.4703976054},
{"learn":[3.912769674],"iteration":501,"passed_time":0.4728708717,"remaining_time":0.4691029763},
{"learn":[3.909373788],"iteration":502,"passed_time":0.473546495,"remaining_time":0.467897829},
{"learn":[3.906706036],"iteration":503,"passed_time":0.4745104194,"remaining_time":0.466978508},
{"learn":[3.903895664],"iteration":504,"passed_time":0.4752131947,"remaining_time":0.4658030324},
{"learn":[3.902982967],"iteration":505,"passed_time":0.4758127421,"remaining_time":0.4645286455},
{"learn":[3.900905528],"iteration":506,"passed_time":0.47641775,"remaining_time":0.4632622303},
{"learn":[3.897463465],"iteration":507,"passed_time":0.4770267355,"remaining_time":0.4620022714},
{"learn":[3.895918033],"iteration":508,"passed_time":0.4776100919,"remaining_time":0.4607201476},
{"learn":[3.893921936],"iteration":509,"passed_time":0.4782040887,"remaining_time":0.4594509872},
{"learn":[3.890237934],"iteration":510,"passed_time":0.4788192961,"remaining_time":0.4582047667},
{"learn":[3.887311613],"iteration":511,"passed_time":0.4794162585,"remaining_time":0.4569436214},
{"learn":[3.884869735],"iteration":512,"passed_time":0.4802774467,"remaining_time":0.4559358997},
{"learn":[3.882101231],"iteration":513,"passed_time":0.480888967,"remaining_time":0.4546926808},
{"learn":[3.88060368],"iteration":514,"passed_time":0.4815735831,"remaining_time":0.453520753},
{"learn":[3.877726076],"iteration":515,"passed_time":0.4822147602,"remaining_time":0.4523099689},
{"learn":[3.874938145],"iteration":516,"passed_time":0.4828321518,"remaining_time":0.4510791669},
{"learn":[3.874340833],"iteration":517,"passed_time":0.4834375003,"remaining_time":0.4498395273},
{"learn":[3.873105224],"iteration":518,"passed_time":0.4840212475,"remaining_time":0.4485823122},
{"learn":[3.869800236],"iteration":519,"passed_time":0.4846567637,"remaining_time":0.4473754742},
{"learn":[3.867932518],"iteration":520,"passed_time":0.4852393386,"remaining_time":0.4461221559},
{"learn":[3.866666962],"iteration":521,"passed_time":0.4860559155,"remaining_time":0.445085685},
{"learn":[3.865527652],"iteration":522,"passed_time":0.4868461378,"remaining_time":0.4440260186},
{"learn":[3.861900081],"iteration":523,"passed_time":0.4875313191,"remaining_time":0.4428719616},
{"learn":[3.858502887],"iteration":524,"passed_time":0.4882223412,"remaining_time":0.4417249754},
{"learn":[3.858335097],"iteration":525,"passed_time":0.4888851497,"remaining_time":0.4405542984},
{"learn":[3.855719306],"iteration":526,"passed_time":0.4895824442,"remaining_time":0.4394165012},
{"learn":[3.855137428],"iteration":527,"passed_time":0.4902970919,"remaining_time":0.4382958852},
{"learn":[3.851985706],"iteration":528,"passed_time":0.4910522822,"remaining_time":0.4372129015},
{"learn":[3.851051809],"iteration":529,"passed_time":0.4917030078,"remaining_time":0.4360385164},
{"learn":[3.850679146],"iteration":530,"passed_time":0.4924169489,"remaining_time":0.4349219379},
{"learn":[3.848179484],"iteration":531,"passed_time":0.4933787699,"remaining_time":0.4340249329},
{"learn":[3.844551071],"iteration":532,"passed_time":0.4941224431,"remaining_time":0.4329365496},
{"learn":[3.841604794],"iteration":533,"passed_time":0.4948142969,"remaining_time":0.4318042366},
{"learn":[3.83969656],"iteration":534,"passed_time":0.4955282135,"remaining_time":0.4306927463},
{"learn":[3.836811463],"iteration":535,"passed_time":0.4963000854,"remaining_time":0.4296329097},
{"learn":[3.834182551],"iteration":536,"passed_time":0.4969992184,"remaining_time":0.4285114304},
{"learn":[3.828012842],"iteration":537,"passed_time":0.497608274,"remaining_time":0.4273141684},
{"learn":[3.826636176],"iteration":538,"passed_time":0.4981979525,"remaining_time":0.426102516},
{"learn":[3.826189798],"iteration":539,"passed_time":0.4988746125,"remaining_time":0.4249672625},
{"learn":[3.824104738],"iteration":540,"passed_time":0.4995457222,"remaining_time":0.4238289953},
{"learn":[3.82300218],"iteration":541,"passed_time":0.5001868489,"remaining_time":0.4226671158},
{"learn":[3.817146402],"iteration":542,"passed_time":0.5008081078,"remaining_time":0.4214904333},
{"learn":[3.814638044],"iteration":543,"passed_time":0.5014072945,"remaining_time":0.420297291},
{"learn":[3.812979573],"iteration":544,"passed_time":0.5020206384,"remaining_time":0.4191181476},
{"learn":[3.811938825],"iteration":545,"passed_time":0.5026236424,"remaining_time":0.4179324792},
{"learn":[3.811479418],"iteration":546,"passed_time":0.5032193124,"remaining_time":0.4167428675},
{"learn":[3.80742981],"iteration":547,"passed_time":0.5038086703,"remaining_time":0.4155502171},
{"learn":[3.805097043],"iteration":548,"passed_time":0.5044271339,"remaining_time":0.4143836747},
{"learn":[3.801577232],"iteration":549,"passed_time":0.5050710412,"remaining_time":0.4132399428},
{"learn":[3.799762083],"iteration":550,"passed_time":0.5056975001,"remaining_time":0.4120838068},
{"learn":[3.796393455],"iteration":551,"passed_time":0.506312427,"remaining_time":0.4109202306},
{"learn":[3.793486459],"iteration":552,"passed_time":0.5069164429,"remaining_time":0.4097498191},
{"learn":[3.792006091],"iteration":553,"passed_time":0.5075132751,"remaining_time":0.4085756692},
{"learn":[3.78932128],"iteration":554,"passed_time":0.5081193851,"remaining_time":0.4074110385},
{"learn":[3.787581812],"iteration":555,"passed_time":0.5087878945,"remaining_time":0.4062982467},
{"learn":[3.785308865],"iteration":556,"passed_time":0.5094041639,"remaining_time":0.405145502},
{"learn":[3.78465475],"iteration":557,"passed_time":0.5099808275,"remaining_time":0.4039633078},
{"learn":[3.780498869],"iteration":558,"passed_time":0.5107074381,"remaining_time":0.4029015746},
{"learn":[3.778734909],"iteration":559,"passed_time":0.5114378306,"remaining_time":0.4018440098},
{"learn":[3.778652349],"iteration":560,"passed_time":0.512195015,"remaining_time":0.4008085768},
{"learn":[3.777928006],"iteration":561,"passed_time":0.5128963131,"remaining_time":0.3997305785},
{"learn":[3.776131406],"iteration":562,"passed_time":0.5136314137,"remaining_time":0.3986801559},
{"learn":[3.772925617],"iteration":563,"passed_time":0.5144131798,"remaining_time":0.3976669262},
{"learn":[3.7727745],"iteration":564,"passed_time":0.5151564526,"remaining_time":0.3966248794},
{"learn":[3.771763073],"iteration":565,"passed_time":0.5158506709,"remaining_time":0.3955462741},
{"learn":[3.768738162],"iteration":566,"passed_time":0.516537305,"remaining_time":0.3944632329},
{"learn":[3.767220794],"iteration":567,"passed_time":0.5172270149,"remaining_time":0.3933839268},
{"learn":[3.766691102],"iteration":568,"passed_time":0.5180367296,"remaining_time":0.3923968901},
{"learn":[3.766259335],"iteration":569,"passed_time":0.518721846,"remaining_time":0.3913164803},
{"learn":[3.76116362],"iteration":570,"passed_time":0.5193529939,"remaining_time":0.3901969079},
{"learn":[3.758633056],"iteration":571,"passed_time":0.5200111635,"remaining_time":0.3890992622},
{"learn":[3.754603809],"iteration":572,"passed_time":0.5207095348,"remaining_time":0.3880331088},
{"learn":[3.754070549],"iteration":573,"passed_time":0.5213509426,"remaining_time":0.3869259609},
{"learn":[3.750534319],"iteration":574,"passed_time":0.5220399011,"remaining_time":0.3858555791},
{"learn":[3.746491516],"iteration":575,"passed_time":0.5226622522,"remaining_time":0.3847374912},
{"learn":[3.744210544],"iteration":576,"passed_time":0.5233245544,"remaining_time":0.3836504099},
{"learn":[3.742929991],"iteration":577,"passed_time":0.5240439562,"remaining_time":0.382606487},
{"learn":[3.740402992],"iteration":578,"passed_time":0.524705728,"remaining_time":0.3815217815},
{"learn":[3.739644243],"iteration":579,"passed_time":0.5253948218,"remaining_time":0.3804583192},
{"learn":[3.737529404],"iteration":580,"passed_time":0.5260188808,"remaining_time":0.3793492445},
{"learn":[3.737196923],"iteration":581,"passed_time":0.5266853012,"remaining_time":0.378272261},
{"learn":[3.733954464],"iteration":582,"passed_time":0.527412949,"remaining_time":0.3772404798},
{"learn":[3.731608623],"iteration":583,"passed_time":0.5281767358,"remaining_time":0.376235483},
{"learn":[3.729843952],"iteration":584,"passed_time":0.5288784634,"remaining_time":0.375187286},
{"learn":[3.727223798],"iteration":585,"passed_time":0.5295498336,"remaining_time":0.3741188244},
{"learn":[3.725351667],"iteration":586,"passed_time":0.530164029,"remaining_time":0.3730114889},
{"learn":[3.725026912],"iteration":587,"passed_time":0.5307655803,"remaining_time":0.3718969712},
{"learn":[3.721974565],"iteration":588,"passed_time":0.5314555558,"remaining_time":0.3708458971},
{"learn":[3.720269493],"iteration":589,"passed_time":0.5321064511,"remaining_time":0.3697688898},
{"learn":[3.718907466],"iteration":590,"passed_time":0.5327269386,"remaining_time":0.3686722807},
{"learn":[3.715602912],"iteration":591,"passed_time":0.5333830596,"remaining_time":0.3676018384},
{"learn":[3.714463059],"iteration":592,"passed_time":0.5340259797,"remaining_time":0.3665237331},
{"learn":[3.710802077],"iteration":593,"passed_time":0.5346673421,"remaining_time":0.3654460285},
{"learn":[3.708032435],"iteration":594,"passed_time":0.5353455203,"remaining_time":0.36439485},
{"learn":[3.703788939],"iteration":595,"passed_time":0.5359924735,"remaining_time":0.3633237572},
{"learn":[3.702500944],"iteration":596,"passed_time":0.5366125248,"remaining_time":0.3622359255},
{"learn":[3.698196925],"iteration":597,"passed_time":0.5372813999,"remaining_time":0.3611824795},
{"learn":[3.69658891],"iteration":598,"passed_time":0.538001488,"remaining_time":0.3601646022},
{"learn":[3.696124066],"iteration":599,"passed_time":0.5387049242,"remaining_time":0.3591366162},
{"learn":[3.693537052],"iteration":600,"passed_time":0.5394163207,"remaining_time":0.3581149949},
{"learn":[3.691343275],"iteration":601,"passed_time":0.5401325718,"remaining_time":0.3570976139},
{"learn":[3.690973831],"iteration":602,"passed_time":0.5408833837,"remaining_time":0.3561039856},
{"learn":[3.686151073],"iteration":603,"passed_time":0.5415686602,"remaining_time":0.3550681944},
{"learn":[3.683921982],"iteration":604,"passed_time":0.5422940384,"remaining_time":0.3540597441},
{"learn":[3.679975271],"iteration":605,"passed_time":0.5429500285,"remaining_time":0.3530071142},
{"learn":[3.674047638],"iteration":606,"passed_time":0.5436328756,"remaining_time":0.3519731798},
{"learn":[3.673151794],"iteration":607,"passed_time":0.5442907848,"remaining_time":0.3509243217},
{"learn":[3.670953108],"iteration":608,"passed_time":0.5449931737,"remaining_time":0.3499053053},
{"learn":[3.6703947],"iteration":609,"passed_time":0.5456438943,"remaining_time":0.3488542931},
{"learn":[3.668433805],"iteration":610,"passed_time":0.5463679798,"remaining_time":0.3478512997},
{"learn":[3.668304956],"iteration":611,"passed_time":0.5471353984,"remaining_time":0.3468766905},
{"learn":[3.667880012],"iteration":612,"passed_time":0.547825429,"remaining_time":0.3458539005},
{"learn":[3.667282264],"iteration":613,"passed_time":0.5484486217,"remaining_time":0.3447901758},
{"learn":[3.664611483],"iteration":614,"passed_time":0.5493666987,"remaining_time":0.3439124862},
{"learn":[3.662543394],"iteration":615,"passed_time":0.5500558676,"remaining_time":0.3428919694},
{"learn":[3.659041959],"iteration":616,"passed_time":0.5508426897,"remaining_time":0.3419331445},
{"learn":[3.656868545],"iteration":617,"passed_time":0.5516151217,"remaining_time":0.3409659814},
{"learn":[3.654785614],"iteration":618,"passed_time":0.5524512982,"remaining_time":0.3400386828},
{"learn":[3.654566096],"iteration":619,"passed_time":0.5530870089,"remaining_time":0.3389888119},
{"learn":[3.651007045],"iteration":620,"passed_time":0.5537143595,"remaining_time":0.3379351727},
{"learn":[3.648921786],"iteration":621,"passed_time":0.5543283245,"remaining_time":0.3368747696},
{"learn":[3.647655706],"iteration":622,"passed_time":0.5549291244,"remaining_time":0.3358078329},
{"learn":[3.647241144],"iteration":623,"passed_time":0.5556377302,"remaining_time":0.3348073502},
{"learn":[3.644195689],"iteration":624,"passed_time":0.5564495438,"remaining_time":0.3338697263},
{"learn":[3.642632246],"iteration":625,"passed_time":0.5571665861,"remaining_time":0.3328758837},
{"learn":[3.642523322],"iteration":626,"passed_time":0.5576882845,"remaining_time":0.3317667147},
{"learn":[3.641494659],"iteration":627,"passed_time":0.5584341266,"remaining_time":0.3307921896},
{"learn":[3.63976496],"iteration":628,"passed_time":0.5590677047,"remaining_time":0.3297521756},
{"learn":[3.637945652],"iteration":629,"passed_time":0.5597147531,"remaining_time":0.3287213629},
{"learn":[3.636233667],"iteration":630,"passed_time":0.5603073772,"remaining_time":0.3276599401},
{"learn":[3.635304404],"iteration":631,"passed_time":0.5609205006,"remaining_time":0.3266119371},
{"learn":[3.632234951],"iteration":632,"passed_time":0.5615345658,"remaining_time":0.3255658541},
{"learn":[3.631630987],"iteration":633,"passed_time":0.5622915746,"remaining_time":0.3246036535},
{"learn":[3.630301009],"iteration":634,"passed_time":0.5631617001,"remaining_time":0.323707119},
{"learn":[3.629077964],"iteration":635,"passed_time":0.563836201,"remaining_time":0.3226987062},
{"learn":[3.628004522],"iteration":636,"passed_time":0.5645406689,"remaining_time":0.3217084188},
{"learn":[3.625062876],"iteration":637,"passed_time":0.5652437908,"remaining_time":0.3207182637},
{"learn":[3.624917986],"iteration":638,"passed_time":0.5658506121,"remaining_time":0.3196746024},
{"learn":[3.622887087],"iteration":639,"passed_time":0.5664572531,"remaining_time":0.3186322049},
{"learn":[3.621220865],"iteration":640,"passed_time":0.5670591049,"remaining_time":0.3175884846},
{"learn":[3.621143844],"iteration":641,"passed_time":0.5676553059,"remaining_time":0.3165429899},
{"learn":[3.620822821],"iteration":642,"passed_time":0.5685040242,"remaining_time":0.3156390928},
{"learn":[3.619202826],"iteration":643,"passed_time":0.5691940946,"remaining_time":0.3146476672},
{"learn":[3.618204882],"iteration":644,"passed_time":0.5699039832,"remaining_time":0.3136680838},
{"learn":[3.614259666],"iteration":645,"passed_time":0.5706537042,"remaining_time":0.312711163},
{"learn":[3.613415661],"iteration":646,"passed_time":0.5715011461,"remaining_time":0.3118081987},
{"learn":[3.611096773],"iteration":647,"passed_time":0.572116664,"remaining_time":0.3107794224},
{"learn":[3.610820695],"iteration":648,"passed_time":0.5728424167,"remaining_time":0.3098115382},
{"learn":[3.609290065],"iteration":649,"passed_time":0.5735337961,"remaining_time":0.3088258902},
{"learn":[3.60897947],"iteration":650,"passed_time":0.5741377019,"remaining_time":0.3077942519},
{"learn":[3.606570702],"iteration":651,"passed_time":0.5749454014,"remaining_time":0.3068726989},
{"learn":[3.606292637],"iteration":652,"passed_time":0.5756658765,"remaining_time":0.3059051442},
{"learn":[3.602753838],"iteration":653,"passed_time":0.5763325662,"remaining_time":0.3049098897},
{"learn":[3.599755869],"iteration":654,"passed_time":0.5770600684,"remaining_time":0.3039476696},
{"learn":[3.599509575],"iteration":655,"passed_time":0.5777151121,"remaining_time":0.3029481685},
{"learn":[3.595337722],"iteration":656,"passed_time":0.5783529628,"remaining_time":0.3019407401},
{"learn":[3.595168561],"iteration":657,"passed_time":0.5790184263,"remaining_time":0.3009487869},
{"learn":[3.59290559],"iteration":658,"passed_time":0.5796402564,"remaining_time":0.2999352465},
{"learn":[3.592015928],"iteration":659,"passed_time":0.5803494239,"remaining_time":0.298967885},
{"learn":[3.590680403],"iteration":660,"passed_time":0.5810786896,"remaining_time":0.2980116124},
{"learn":[3.590361532],"iteration":661,"passed_time":0.5817267348,"remaining_time":0.2970145564},
{"learn":[3.589069739],"iteration":662,"passed_time":0.5823717993,"remaining_time":0.2960170383},
{"learn":[3.585010186],"iteration":663,"passed_time":0.5830997722,"remaining_time":0.2950625353},
{"learn":[3.582997552],"iteration":664,"passed_time":0.5838861171,"remaining_time":0.2941381191},
{"learn":[3.582119256],"iteration":665,"passed_time":0.5845624612,"remaining_time":0.293158952},
{"learn":[3.579019356],"iteration":666,"passed_time":0.585198809,"remaining_time":0.2921607247},
{"learn":[3.57719559],"iteration":667,"passed_time":0.5858086461,"remaining_time":0.291150405},
{"learn":[3.574050046],"iteration":668,"passed_time":0.5864138443,"remaining_time":0.2901389873},
{"learn":[3.572204518],"iteration":669,"passed_time":0.5871109234,"remaining_time":0.2891740369},
{"learn":[3.569508025],"iteration":670,"passed_time":0.5879455858,"remaining_time":0.2882773438},
{"learn":[3.566268704],"iteration":671,"passed_time":0.5886722117,"remaining_time":0.2873281033},
{"learn":[3.562564052],"iteration":672,"passed_time":0.5894335885,"remaining_time":0.2863964093},
{"learn":[3.561173586],"iteration":673,"passed_time":0.590079665,"remaining_time":0.2854094522},
{"learn":[3.559551904],"iteration":674,"passed_time":0.590701475,"remaining_time":0.2844118213},
{"learn":[3.558593054],"iteration":675,"passed_time":0.5913035873,"remaining_time":0.2834058614},
{"learn":[3.555647008],"iteration":676,"passed_time":0.5919075632,"remaining_time":0.2824019836},
{"learn":[3.553100059],"iteration":677,"passed_time":0.5925123005,"remaining_time":0.2813996472},
{"learn":[3.55085578],"iteration":678,"passed_time":0.5931649947,"remaining_time":0.2804211536},
{"learn":[3.550737965],"iteration":679,"passed_time":0.5938543389,"remaining_time":0.2794608654},
{"learn":[3.549408772],"iteration":680,"passed_time":0.5946158717,"remaining_time":0.278535188},
{"learn":[3.547390589],"iteration":681,"passed_time":0.5953438145,"remaining_time":0.2775943299},
{"learn":[3.54723575],"iteration":682,"passed_time":0.5960349569,"remaining_time":0.2766370151},
{"learn":[3.543988891],"iteration":683,"passed_time":0.5970264243,"remaining_time":0.2758192253},
{"learn":[3.543868508],"iteration":684,"passed_time":0.5976573217,"remaining_time":0.2748351188},
{"learn":[3.542752124],"iteration":685,"passed_time":0.5982538133,"remaining_time":0.2738362936},
{"learn":[3.541334315],"iteration":686,"passed_time":0.59886345,"remaining_time":0.2728446286},
{"learn":[3.540208266],"iteration":687,"passed_time":0.5996466595,"remaining_time":0.2719327875},
{"learn":[3.537730983],"iteration":688,"passed_time":0.6003793518,"remaining_time":0.2709985173},
{"learn":[3.53419867],"iteration":689,"passed_time":0.6011104572,"remaining_time":0.2700641185},
{"learn":[3.532628335],"iteration":690,"passed_time":0.6019478235,"remaining_time":0.2691778256},
{"learn":[3.532204987],"iteration":691,"passed_time":0.6027622021,"remaining_time":0.2682814425},
{"learn":[3.530618147],"iteration":692,"passed_time":0.6034249805,"remaining_time":0.2673181371},
{"learn":[3.528909306],"iteration":693,"passed_time":0.6040498363,"remaining_time":0.2663389768},
{"learn":[3.526700678],"iteration":694,"passed_time":0.6046717566,"remaining_time":0.2653595478},
{"learn":[3.526439574],"iteration":695,"passed_time":0.605268188,"remaining_time":0.2643700132},
{"learn":[3.525784216],"iteration":696,"passed_time":0.6060091864,"remaining_time":0.2634444526},
{"learn":[3.524112693],"iteration":697,"passed_time":0.6066871135,"remaining_time":0.2624921322},
{"learn":[3.522813541],"iteration":698,"passed_time":0.6073444616,"remaining_time":0.2615317352},
{"learn":[3.519148203],"iteration":699,"passed_time":0.6080142997,"remaining_time":0.260577557},
{"learn":[3.517236747],"iteration":700,"passed_time":0.6088396233,"remaining_time":0.2596905098},
{"learn":[3.515603888],"iteration":701,"passed_time":0.6095412861,"remaining_time":0.2587511443},
{"learn":[3.51263524],"iteration":702,"passed_time":0.6101971012,"remaining_time":0.2577930854},
{"learn":[3.51123442],"iteration":703,"passed_time":0.6108041931,"remaining_time":0.2568153994},
{"learn":[3.50828027],"iteration":704,"passed_time":0.6114208232,"remaining_time":0.2558427558},
{"learn":[3.508265537],"iteration":705,"passed_time":0.6118052689,"remaining_time":0.2547744321},
{"learn":[3.506774876],"iteration":706,"passed_time":0.6125686903,"remaining_time":0.2538651008},
{"learn":[3.50552068],"iteration":707,"passed_time":0.6132470485,"remaining_time":0.2529210991},
{"learn":[3.501973993],"iteration":708,"passed_time":0.6139059592,"remaining_time":0.2519698648},
{"learn":[3.498880354],"iteration":709,"passed_time":0.6148225187,"remaining_time":0.2511246907},
{"learn":[3.497370959],"iteration":710,"passed_time":0.6155188964,"remaining_time":0.2501898186},
{"learn":[3.496050455],"iteration":711,"passed_time":0.6162666321,"remaining_time":0.2492763905},
{"learn":[3.495630067],"iteration":712,"passed_time":0.6169025591,"remaining_time":0.2483184214},
{"learn":[3.49550669],"iteration":713,"passed_time":0.6175203815,"remaining_time":0.2473541024},
{"learn":[3.493652375],"iteration":714,"passed_time":0.6181574708,"remaining_time":0.2463984324},
{"learn":[3.491915684],"iteration":715,"passed_time":0.6188505021,"remaining_time":0.2454658416},
{"learn":[3.490303956],"iteration":716,"passed_time":0.619503948,"remaining_time":0.2445182947},
{"learn":[3.488363853],"iteration":717,"passed_time":0.6201316392,"remaining_time":0.2435614516},
{"learn":[3.485483936],"iteration":718,"passed_time":0.6208320193,"remaining_time":0.2426339324},
{"learn":[3.483763466],"iteration":719,"passed_time":0.6216149329,"remaining_time":0.2417391406},
{"learn":[3.481642352],"iteration":720,"passed_time":0.6223755784,"remaining_time":0.2408360421},
{"learn":[3.479826119],"iteration":721,"passed_time":0.6230515019,"remaining_time":0.2399007168},
{"learn":[3.478588728],"iteration":722,"passed_time":0.6238167765,"remaining_time":0.2390003418},
{"learn":[3.475390887],"iteration":723,"passed_time":0.6246170277,"remaining_time":0.2381136735},
{"learn":[3.472636852],"iteration":724,"passed_time":0.6252935324,"remaining_time":0.2371803054},
{"learn":[3.47061883],"iteration":725,"passed_time":0.6260380974,"remaining_time":0.2362733315},
{"learn":[3.46953149],"iteration":726,"passed_time":0.6267286489,"remaining_time":0.2353465215},
{"learn":[3.467217162],"iteration":727,"passed_time":0.6274880025,"remaining_time":0.2344460669},
{"learn":[3.465686216],"iteration":728,"passed_time":0.6281969493,"remaining_time":0.233527261},
{"learn":[3.462631216],"iteration":729,"passed_time":0.6288156133,"remaining_time":0.2325756378},
{"learn":[3.461451053],"iteration":730,"passed_time":0.629413748,"remaining_time":0.231617371},
{"learn":[3.458950469],"iteration":731,"passed_time":0.6300167019,"remaining_time":0.2306618526},
{"learn":[3.458072145],"iteration":732,"passed_time":0.6306359467,"remaining_time":0.2297132302},
{"learn":[3.454364268],"iteration":733,"passed_time":0.6314233236,"remaining_time":0.2288264361},
{"learn":[3.453243406],"iteration":734,"passed_time":0.6321290345,"remaining_time":0.2279104682},
{"learn":[3.453017963],"iteration":735,"passed_time":0.6327574972,"remaining_time":0.2269673631},
{"learn":[3.45201581],"iteration":736,"passed_time":0.6333691578,"remaining_time":0.226019116},
{"learn":[3.449510107],"iteration":737,"passed_time":0.6340258746,"remaining_time":0.2250877766},
{"learn":[3.447189189],"iteration":738,"passed_time":0.6347172875,"remaining_time":0.2241694344},
{"learn":[3.446423605],"iteration":739,"passed_time":0.6354690466,"remaining_time":0.2232729083},
{"learn":[3.445531987],"iteration":740,"passed_time":0.636075397,"remaining_time":0.2223259485},
{"learn":[3.445328199],"iteration":741,"passed_time":0.6366933997,"remaining_time":0.2213839584},
{"learn":[3.443327544],"iteration":742,"passed_time":0.6373046996,"remaining_time":0.2204405219},
{"learn":[3.441475798],"iteration":743,"passed_time":0.6380503667,"remaining_time":0.2195442122},
{"learn":[3.439046501],"iteration":744,"passed_time":0.6386706438,"remaining_time":0.2186053881},
{"learn":[3.435899469],"iteration":745,"passed_time":0.6392781965,"remaining_time":0.2176630857},
{"learn":[3.433988352],"iteration":746,"passed_time":0.639900778,"remaining_time":0.2167267695},
{"learn":[3.433413263],"iteration":747,"passed_time":0.6405130498,"remaining_time":0.2157878189},
{"learn":[3.429944699],"iteration":748,"passed_time":0.6411226765,"remaining_time":0.2148488542},
{"learn":[3.429291634],"iteration":749,"passed_time":0.6417160721,"remaining_time":0.2139053574},
{"learn":[3.429175603],"iteration":750,"passed_time":0.6423139062,"remaining_time":0.2129642645},
{"learn":[3.428780323],"iteration":751,"passed_time":0.6428996873,"remaining_time":0.2120201096},
{"learn":[3.423893341],"iteration":752,"passed_time":0.6435163371,"remaining_time":0.2110870322},
{"learn":[3.421024316],"iteration":753,"passed_time":0.6441654193,"remaining_time":0.2101653755},
{"learn":[3.420969872],"iteration":754,"passed_time":0.6447585945,"remaining_time":0.2092262989},
{"learn":[3.419544785],"iteration":755,"passed_time":0.6453658768,"remaining_time":0.2082926904},
{"learn":[3.417057977],"iteration":756,"passed_time":0.6459622381,"remaining_time":0.2073564384},
{"learn":[3.415160245],"iteration":757,"passed_time":0.6465655928,"remaining_time":0.2064233159},
{"learn":[3.412854597],"iteration":758,"passed_time":0.6471630562,"remaining_time":0.2054891918},
{"learn":[3.410926347],"iteration":759,"passed_time":0.6477879321,"remaining_time":0.2045646101},
{"learn":[3.408963843],"iteration":760,"passed_time":0.6484260132,"remaining_time":0.2036449634},
{"learn":[3.407629634],"iteration":761,"passed_time":0.6490309009,"remaining_time":0.2027156882},
{"learn":[3.404384724],"iteration":762,"passed_time":0.6497376638,"remaining_time":0.2018189074},
{"learn":[3.403041656],"iteration":763,"passed_time":0.6503870766,"remaining_time":0.2009049085},
{"learn":[3.401101731],"iteration":764,"passed_time":0.6510114716,"remaining_time":0.1999839161},
{"learn":[3.400890668],"iteration":765,"passed_time":0.6516135538,"remaining_time":0.199056882},
{"learn":[3.399289941],"iteration":766,"passed_time":0.6522175398,"remaining_time":0.1981312735},
{"learn":[3.399202366],"iteration":767,"passed_time":0.6527956461,"remaining_time":0.1971986848},
{"learn":[3.397447845],"iteration":768,"passed_time":0.6533843027,"remaining_time":0.1962701872},
{"learn":[3.394655341],"iteration":769,"passed_time":0.653980654,"remaining_time":0.1953448707},
{"learn":[3.393228229],"iteration":770,"passed_time":0.6545700921,"remaining_time":0.1944183542},
{"learn":[3.389691197],"iteration":771,"passed_time":0.6551847283,"remaining_time":0.1935001529},
{"learn":[3.389626772],"iteration":772,"passed_time":0.6557627846,"remaining_time":0.192571995},
{"learn":[3.388480222],"iteration":773,"passed_time":0.6563447083,"remaining_time":0.1916458709},
{"learn":[3.388215066],"iteration":774,"passed_time":0.656931331,"remaining_time":0.1907219993},
{"learn":[3.386324358],"iteration":775,"passed_time":0.6575329624,"remaining_time":0.1898033293},
{"learn":[3.383913061],"iteration":776,"passed_time":0.658159782,"remaining_time":0.1888927045},
{"learn":[3.382839768],"iteration":777,"passed_time":0.6587698295,"remaining_time":0.1879780233},
{"learn":[3.381961844],"iteration":778,"passed_time":0.6593718216,"remaining_time":0.187061839},
{"learn":[3.381521703],"iteration":779,"passed_time":0.6599746954,"remaining_time":0.1861467089},
{"learn":[3.380918963],"iteration":780,"passed_time":0.6605630513,"remaining_time":0.1852283076},
{"learn":[3.377139006],"iteration":781,"passed_time":0.6611735197,"remaining_time":0.1843169147},
{"learn":[3.376004372],"iteration":782,"passed_time":0.6617719549,"remaining_time":0.1834029556},
{"learn":[3.373826468],"iteration":783,"passed_time":0.6623679756,"remaining_time":0.1824891361},
{"learn":[3.373546786],"iteration":784,"passed_time":0.6629652386,"remaining_time":0.1815764666},
{"learn":[3.372109181],"iteration":785,"passed_time":0.6636366736,"remaining_time":0.1806847941},
{"learn":[3.370764924],"iteration":786,"passed_time":0.6642679117,"remaining_time":0.179782802},
{"learn":[3.367833107],"iteration":787,"passed_time":0.6648926473,"remaining_time":0.1788797478},
{"learn":[3.36450404],"iteration":788,"passed_time":0.6655039272,"remaining_time":0.1779738005},
{"learn":[3.361794558],"iteration":789,"passed_time":0.6661154174,"remaining_time":0.1770686553},
{"learn":[3.356880529],"iteration":790,"passed_time":0.6667318171,"remaining_time":0.1761655497},
{"learn":[3.353843509],"iteration":791,"passed_time":0.6673474453,"remaining_time":0.1752629654},
{"learn":[3.353640253],"iteration":792,"passed_time":0.667939308,"remaining_time":0.1743549013},
{"learn":[3.353055088],"iteration":793,"passed_time":0.6685148695,"remaining_time":0.1734434044},
{"learn":[3.351415617],"iteration":794,"passed_time":0.6691214103,"remaining_time":0.172540741},
{"learn":[3.349169061],"iteration":795,"passed_time":0.6697200259,"remaining_time":0.1716367906},
{"learn":[3.346211014],"iteration":796,"passed_time":0.6703235309,"remaining_time":0.1707348517},
{"learn":[3.344560452],"iteration":797,"passed_time":0.6709174676,"remaining_time":0.1698312387},
{"learn":[3.344445461],"iteration":798,"passed_time":0.6715169649,"remaining_time":0.1689297997},
{"learn":[3.342608898],"iteration":799,"passed_time":0.6721403479,"remaining_time":0.168035087},
{"learn":[3.339572899],"iteration":800,"passed_time":0.6727466583,"remaining_time":0.1671368102},
{"learn":[3.339309302],"iteration":801,"passed_time":0.6733340224,"remaining_time":0.1662345841},
{"learn":[3.33698088],"iteration":802,"passed_time":0.6739371867,"remaining_time":0.1653370184},
{"learn":[3.334746342],"iteration":803,"passed_time":0.6745341291,"remaining_time":0.1644386683},
{"learn":[3.332048511],"iteration":804,"passed_time":0.6751308311,"remaining_time":0.1635410088},
{"learn":[3.331932544],"iteration":805,"passed_time":0.6757468801,"remaining_time":0.1626487528},
{"learn":[3.330541133],"iteration":806,"passed_time":0.6763894599,"remaining_time":0.1617635263},
{"learn":[3.329124989],"iteration":807,"passed_time":0.6770086749,"remaining_time":0.1608733485},
{"learn":[3.32583918],"iteration":808,"passed_time":0.677602321,"remaining_time":0.1599778039},
{"learn":[3.325287299],"iteration":809,"passed_time":0.6782596393,"remaining_time":0.1590979401},
{"learn":[3.322745162],"iteration":810,"passed_time":0.6788716005,"remaining_time":0.1582080549},
{"learn":[3.319733662],"iteration":811,"passed_time":0.6794827,"remaining_time":0.1573186547},
{"learn":[3.318080007],"iteration":812,"passed_time":0.6801415008,"remaining_time":0.156440911},
{"learn":[3.317179538],"iteration":813,"passed_time":0.6807381026,"remaining_time":0.1555494927},
{"learn":[3.315685949],"iteration":814,"passed_time":0.6813301957,"remaining_time":0.1546577745},
{"learn":[3.314944576],"iteration":815,"passed_time":0.681934402,"remaining_time":0.153769522},
{"learn":[3.312369052],"iteration":816,"passed_time":0.6825495694,"remaining_time":0.1528844201},
{"learn":[3.312321621],"iteration":817,"passed_time":0.6830187573,"remaining_time":0.1519674986},
{"learn":[3.309465776],"iteration":818,"passed_time":0.6836148882,"remaining_time":0.151079725},
{"learn":[3.308307377],"iteration":819,"passed_time":0.6842339329,"remaining_time":0.1501976926},
{"learn":[3.308076804],"iteration":820,"passed_time":0.6848281801,"remaining_time":0.1493108943},
{"learn":[3.305643326],"iteration":821,"passed_time":0.6854328173,"remaining_time":0.1484270578},
{"learn":[3.304154814],"iteration":822,"passed_time":0.6860298599,"remaining_time":0.1475422663},
{"learn":[3.303076321],"iteration":823,"passed_time":0.6866202197,"remaining_time":0.146656746},
{"learn":[3.301746372],"iteration":824,"passed_time":0.6872176431,"remaining_time":0.1457734394},
{"learn":[3.301345455],"iteration":825,"passed_time":0.6878079328,"remaining_time":0.1448893224},
{"learn":[3.299181039],"iteration":826,"passed_time":0.6883981523,"remaining_time":0.1440059013},
{"learn":[3.297989357],"iteration":827,"passed_time":0.6889991325,"remaining_time":0.1431254237},
{"learn":[3.294775182],"iteration":828,"passed_time":0.6896167144,"remaining_time":0.1422490448},
{"learn":[3.293840636],"iteration":829,"passed_time":0.6902036477,"remaining_time":0.1413670122},
{"learn":[3.289279397],"iteration":830,"passed_time":0.690830838,"remaining_time":0.1404938768},
{"learn":[3.286204979],"iteration":831,"passed_time":0.6914392323,"remaining_time":0.1396175373},
{"learn":[3.284833593],"iteration":832,"passed_time":0.6921424425,"remaining_time":0.1387608498},
{"learn":[3.283519914],"iteration":833,"passed_time":0.6927648336,"remaining_time":0.1378884441},
{"learn":[3.282853026],"iteration":834,"passed_time":0.6934018428,"remaining_time":0.1370195258},
{"learn":[3.281944673],"iteration":835,"passed_time":0.694012261,"remaining_time":0.1361459459},
{"learn":[3.279764865],"iteration":836,"passed_time":0.694620996,"remaining_time":0.1352726671},
{"learn":[3.277468839],"iteration":837,"passed_time":0.6952263946,"remaining_time":0.1343993746},
{"learn":[3.277124974],"iteration":838,"passed_time":0.6958260522,"remaining_time":0.1335256191},
{"learn":[3.275636037],"iteration":839,"passed_time":0.6964197183,"remaining_time":0.1326513749},
{"learn":[3.274413635],"iteration":840,"passed_time":0.6970155286,"remaining_time":0.1317782034},
{"learn":[3.272636087],"iteration":841,"passed_time":0.6976209773,"remaining_time":0.1309074993},
{"learn":[3.269644466],"iteration":842,"passed_time":0.6982370163,"remaining_time":0.1300393969},
{"learn":[3.26852083],"iteration":843,"passed_time":0.6988340088,"remaining_time":0.1291683713},
{"learn":[3.267820927],"iteration":844,"passed_time":0.6994231062,"remaining_time":0.1282965461},
{"learn":[3.267331099],"iteration":845,"passed_time":0.7000274628,"remaining_time":0.127428167},
{"learn":[3.267231014],"iteration":846,"passed_time":0.7006147067,"remaining_time":0.1265573201},
{"learn":[3.267158695],"iteration":847,"passed_time":0.7011962797,"remaining_time":0.1256861256},
{"learn":[3.264718705],"iteration":848,"passed_time":0.7018066578,"remaining_time":0.1248207366},
{"learn":[3.261678512],"iteration":849,"passed_time":0.7024179377,"remaining_time":0.1239561067},
{"learn":[3.261368381],"iteration":850,"passed_time":0.703001755,"remaining_time":0.1230872638},
{"learn":[3.260128799],"iteration":851,"passed_time":0.7035972647,"remaining_time":0.1222211211},
{"learn":[3.258972952],"iteration":852,"passed_time":0.7041776454,"remaining_time":0.1213530057},
{"learn":[3.258724846],"iteration":853,"passed_time":0.7047633163,"remaining_time":0.1204864686},
{"learn":[3.25686724],"iteration":854,"passed_time":0.7053586556,"remaining_time":0.1196222281},
{"learn":[3.255750259],"iteration":855,"passed_time":0.7059552875,"remaining_time":0.1187588334},
{"learn":[3.254915866],"iteration":856,"passed_time":0.7068855478,"remaining_time":0.1179517308},
{"learn":[3.254348625],"iteration":857,"passed_time":0.707555891,"remaining_time":0.1171013246},
{"learn":[3.253408514],"iteration":858,"passed_time":0.7081762382,"remaining_time":0.1162431311},
{"learn":[3.253291714],"iteration":859,"passed_time":0.7087757756,"remaining_time":0.115382103},
{"learn":[3.250186342],"iteration":860,"passed_time":0.7093913738,"remaining_time":0.1145242752},
{"learn":[3.249141318],"iteration":861,"passed_time":0.7099787278,"remaining_time":0.1136624877},
{"learn":[3.246300388],"iteration":862,"passed_time":0.7105783253,"remaining_time":0.1128032799},
{"learn":[3.245205135],"iteration":863,"passed_time":0.7111799968,"remaining_time":0.1119449995},
{"learn":[3.244403535],"iteration":864,"passed_time":0.711778362,"remaining_time":0.1110867964},
{"learn":[3.244211781],"iteration":865,"passed_time":0.7123538233,"remaining_time":0.1102256493},
{"learn":[3.242286347],"iteration":866,"passed_time":0.7129447041,"remaining_time":0.1093675267},
{"learn":[3.239606746],"iteration":867,"passed_time":0.7135325291,"remaining_time":0.1085095551},
{"learn":[3.236773361],"iteration":868,"passed_time":0.7141325374,"remaining_time":0.1076540419},
{"learn":[3.234552446],"iteration":869,"passed_time":0.714721735,"remaining_time":0.1067975006},
{"learn":[3.233724647],"iteration":870,"passed_time":0.7153301694,"remaining_time":0.1059444223},
{"learn":[3.230851485],"iteration":871,"passed_time":0.7159365098,"remaining_time":0.1050915978},
{"learn":[3.227728941],"iteration":872,"passed_time":0.716535426,"remaining_time":0.1042382578},
{"learn":[3.225787575],"iteration":873,"passed_time":0.7171297835,"remaining_time":0.1033848429},
{"learn":[3.222797487],"iteration":874,"passed_time":0.7177435882,"remaining_time":0.1025347983},
{"learn":[3.22137014],"iteration":875,"passed_time":0.7183395788,"remaining_time":0.1016827714},
{"learn":[3.219701963],"iteration":876,"passed_time":0.7189472117,"remaining_time":0.1008329613},
{"learn":[3.21783327],"iteration":877,"passed_time":0.7195847518,"remaining_time":0.09998785845},
{"learn":[3.217713355],"iteration":878,"passed_time":0.7201715448,"remaining_time":0.09913624223},
{"learn":[3.217666091],"iteration":879,"passed_time":0.720768387,"remaining_time":0.09828659823},
{"learn":[3.214962005],"iteration":880,"passed_time":0.7213800176,"remaining_time":0.09743952564},
{"learn":[3.214081828],"iteration":881,"passed_time":0.7219709886,"remaining_time":0.09659022296},
{"learn":[3.213358337],"iteration":882,"passed_time":0.7225677707,"remaining_time":0.09574227539},
{"learn":[3.210850401],"iteration":883,"passed_time":0.723183469,"remaining_time":0.09489737828},
{"learn":[3.207810328],"iteration":884,"passed_time":0.7238120019,"remaining_time":0.09405466691},
{"learn":[3.204935073],"iteration":885,"passed_time":0.7244175708,"remaining_time":0.09320948428},
{"learn":[3.20280198],"iteration":886,"passed_time":0.7250419558,"remaining_time":0.09236723901},
{"learn":[3.200663495],"iteration":887,"passed_time":0.7256549489,"remaining_time":0.09152404761},
{"learn":[3.197301669],"iteration":888,"passed_time":0.7262563899,"remaining_time":0.0906799317},
{"learn":[3.195666943],"iteration":889,"passed_time":0.7268705954,"remaining_time":0.08983793876},
{"learn":[3.193886506],"iteration":890,"passed_time":0.7274719262,"remaining_time":0.08899488211},
{"learn":[3.190601248],"iteration":891,"passed_time":0.7280591901,"remaining_time":0.08815066428},
{"learn":[3.188983797],"iteration":892,"passed_time":0.7286613225,"remaining_time":0.08730880348},
{"learn":[3.187365749],"iteration":893,"passed_time":0.7292549486,"remaining_time":0.08646647041},
{"learn":[3.186160771],"iteration":894,"passed_time":0.7298652465,"remaining_time":0.08562664904},
{"learn":[3.185358981],"iteration":895,"passed_time":0.7304618984,"remaining_time":0.08478575607},
{"learn":[3.183832164],"iteration":896,"passed_time":0.7310538212,"remaining_time":0.08394486465},
{"learn":[3.183106966],"iteration":897,"passed_time":0.7316570757,"remaining_time":0.08310581484},
{"learn":[3.182838152],"iteration":898,"passed_time":0.7322541083,"remaining_time":0.08226659059},
{"learn":[3.180835453],"iteration":899,"passed_time":0.7328703677,"remaining_time":0.08143004086},
{"learn":[3.179957348],"iteration":900,"passed_time":0.7334586436,"remaining_time":0.08059090534},
{"learn":[3.179752966],"iteration":901,"passed_time":0.7340774178,"remaining_time":0.07975563963},
{"learn":[3.178851983],"iteration":902,"passed_time":0.7346661445,"remaining_time":0.07891762571},
{"learn":[3.176748586],"iteration":903,"passed_time":0.7352649405,"remaining_time":0.07808123261},
{"learn":[3.172960988],"iteration":904,"passed_time":0.7359038732,"remaining_time":0.07724957785},
{"learn":[3.172794225],"iteration":905,"passed_time":0.7364991725,"remaining_time":0.07641382143},
{"learn":[3.169996507],"iteration":906,"passed_time":0.7371133379,"remaining_time":0.07558052969},
{"learn":[3.16813015],"iteration":907,"passed_time":0.737723706,"remaining_time":0.07474733585},
{"learn":[3.166920871],"iteration":908,"passed_time":0.7383119218,"remaining_time":0.07391241461},
{"learn":[3.16531606],"iteration":909,"passed_time":0.7388967109,"remaining_time":0.07307769668},
{"learn":[3.162035247],"iteration":910,"passed_time":0.7395032617,"remaining_time":0.07224565345},
{"learn":[3.16189467],"iteration":911,"passed_time":0.740085997,"remaining_time":0.07141180673},
{"learn":[3.161008416],"iteration":912,"passed_time":0.7406857548,"remaining_time":0.07058013216},
{"learn":[3.160560787],"iteration":913,"passed_time":0.7412696823,"remaining_time":0.06974747558},
{"learn":[3.160416261],"iteration":914,"passed_time":0.7418453139,"remaining_time":0.06891459201},
{"learn":[3.15844291],"iteration":915,"passed_time":0.7424545299,"remaining_time":0.0680853499},
{"learn":[3.155040501],"iteration":916,"passed_time":0.7430426354,"remaining_time":0.06725467692},
{"learn":[3.154937548],"iteration":917,"passed_time":0.7436507392,"remaining_time":0.06642631875},
{"learn":[3.153721161],"iteration":918,"passed_time":0.7442470704,"remaining_time":0.06559740229},
{"learn":[3.153170511],"iteration":919,"passed_time":0.7448359474,"remaining_time":0.06476834325},
{"learn":[3.153113601],"iteration":920,"passed_time":0.7454429992,"remaining_time":0.06394136475},
{"learn":[3.150607379],"iteration":921,"passed_time":0.7460519446,"remaining_time":0.06311502351},
{"learn":[3.148408359],"iteration":922,"passed_time":0.7466745762,"remaining_time":0.06229029509},
{"learn":[3.147495728],"iteration":923,"passed_time":0.7472833312,"remaining_time":0.06146486274},
{"learn":[3.146946235],"iteration":924,"passed_time":0.74787315,"remaining_time":0.06063836351},
{"learn":[3.14472738],"iteration":925,"passed_time":0.7484754827,"remaining_time":0.05981337551},
{"learn":[3.144469477],"iteration":926,"passed_time":0.7491222355,"remaining_time":0.0589923659},
{"learn":[3.142975516],"iteration":927,"passed_time":0.7497467206,"remaining_time":0.05817000419},
{"learn":[3.14079113],"iteration":928,"passed_time":0.7503420299,"remaining_time":0.05734583867},
{"learn":[3.138173032],"iteration":929,"passed_time":0.7509522578,"remaining_time":0.05652328822},
{"learn":[3.136352813],"iteration":930,"passed_time":0.7515591993,"remaining_time":0.05570095033},
{"learn":[3.133735004],"iteration":931,"passed_time":0.7522092534,"remaining_time":0.0548822202},
{"learn":[3.1319496],"iteration":932,"passed_time":0.752843908,"remaining_time":0.0540627458},
{"learn":[3.129865343],"iteration":933,"passed_time":0.7534496673,"remaining_time":0.05324162531},
{"learn":[3.129830206],"iteration":934,"passed_time":0.7539233238,"remaining_time":0.05241178187},
{"learn":[3.126676562],"iteration":935,"passed_time":0.7545235825,"remaining_time":0.05159135607},
{"learn":[3.12645665],"iteration":936,"passed_time":0.7551145135,"remaining_time":0.05077077305},
{"learn":[3.126378007],"iteration":937,"passed_time":0.7556894838,"remaining_time":0.04994962473},
{"learn":[3.124621914],"iteration":938,"passed_time":0.7562800741,"remaining_time":0.04913001546},
{"learn":[3.123379018],"iteration":939,"passed_time":0.7568726883,"remaining_time":0.04831102265},
{"learn":[3.123332451],"iteration":940,"passed_time":0.7574530089,"remaining_time":0.04749174019},
{"learn":[3.122432444],"iteration":941,"passed_time":0.7580491698,"remaining_time":0.04667394039},
{"learn":[3.121889006],"iteration":942,"passed_time":0.7586436175,"remaining_time":0.0458565071},
{"learn":[3.121070914],"iteration":943,"passed_time":0.7592304505,"remaining_time":0.04503909452},
{"learn":[3.118444705],"iteration":944,"passed_time":0.7598411393,"remaining_time":0.04422355837},
{"learn":[3.116820458],"iteration":945,"passed_time":0.7604342343,"remaining_time":0.04340745101},
{"learn":[3.114971041],"iteration":946,"passed_time":0.761032349,"remaining_time":0.04259209556},
{"learn":[3.114685138],"iteration":947,"passed_time":0.7616222179,"remaining_time":0.04177674613},
{"learn":[3.113399363],"iteration":948,"passed_time":0.7622377659,"remaining_time":0.04096325191},
{"learn":[3.110575399],"iteration":949,"passed_time":0.762851761,"remaining_time":0.04015009268},
{"learn":[3.110466553],"iteration":950,"passed_time":0.7634627703,"remaining_time":0.03933719847},
{"learn":[3.108691641],"iteration":951,"passed_time":0.7640600233,"remaining_time":0.03852403479},
{"learn":[3.107898017],"iteration":952,"passed_time":0.7646485897,"remaining_time":0.03771089582},
{"learn":[3.105551729],"iteration":953,"passed_time":0.7652560122,"remaining_time":0.03689913686},
{"learn":[3.104824945],"iteration":954,"passed_time":0.7658337679,"remaining_time":0.03608640791},
{"learn":[3.103186704],"iteration":955,"passed_time":0.7664458193,"remaining_time":0.035275749},
{"learn":[3.102330655],"iteration":956,"passed_time":0.7670466591,"remaining_time":0.0344650014},
{"learn":[3.102291298],"iteration":957,"passed_time":0.7676275909,"remaining_time":0.03365381923},
{"learn":[3.100363529],"iteration":958,"passed_time":0.7682263669,"remaining_time":0.03284388013},
{"learn":[3.097871596],"iteration":959,"passed_time":0.7688272568,"remaining_time":0.03203446904},
{"learn":[3.097372213],"iteration":960,"passed_time":0.7694231473,"remaining_time":0.03122528901},
{"learn":[3.095981813],"iteration":961,"passed_time":0.7700121645,"remaining_time":0.03041628093},
{"learn":[3.095347452],"iteration":962,"passed_time":0.7706074137,"remaining_time":0.02960796917},
{"learn":[3.094728409],"iteration":963,"passed_time":0.7711949581,"remaining_time":0.02879981171},
{"learn":[3.094118537],"iteration":964,"passed_time":0.7717974812,"remaining_time":0.02799265476},
{"learn":[3.093793695],"iteration":965,"passed_time":0.7723887829,"remaining_time":0.02718552652},
{"learn":[3.092581602],"iteration":966,"passed_time":0.7730343183,"remaining_time":0.02638069545},
{"learn":[3.091694202],"iteration":967,"passed_time":0.7736420213,"remaining_time":0.02557494285},
{"learn":[3.090298312],"iteration":968,"passed_time":0.7742361684,"remaining_time":0.02476916535},
{"learn":[3.090020107],"iteration":969,"passed_time":0.7748361066,"remaining_time":0.0239640033},
{"learn":[3.088949869],"iteration":970,"passed_time":0.7754201743,"remaining_time":0.02315878996},
{"learn":[3.086700204],"iteration":971,"passed_time":0.776028218,"remaining_time":0.02235472233},
{"learn":[3.086584317],"iteration":972,"passed_time":0.7766216938,"remaining_time":0.02155065337},
{"learn":[3.084850742],"iteration":973,"passed_time":0.7772255294,"remaining_time":0.02074729339},
{"learn":[3.084239948],"iteration":974,"passed_time":0.7778381318,"remaining_time":0.01994456748},
{"learn":[3.082561673],"iteration":975,"passed_time":0.7784367875,"remaining_time":0.01914188822},
{"learn":[3.07991814],"iteration":976,"passed_time":0.7790194727,"remaining_time":0.01833925064},
{"learn":[3.079350277],"iteration":977,"passed_time":0.7796217753,"remaining_time":0.01753750415},
{"learn":[3.077637462],"iteration":978,"passed_time":0.7802405195,"remaining_time":0.01673651778},
{"learn":[3.076733301],"iteration":979,"passed_time":0.7808204093,"remaining_time":0.01593511039},
{"learn":[3.07594065],"iteration":980,"passed_time":0.7814262688,"remaining_time":0.0151346576},
{"learn":[3.072594655],"iteration":981,"passed_time":0.7820331602,"remaining_time":0.01433462005},
{"learn":[3.071977674],"iteration":982,"passed_time":0.7826248326,"remaining_time":0.01353471226},
{"learn":[3.069532634],"iteration":983,"passed_time":0.7832195007,"remaining_time":0.01273527643},
{"learn":[3.068870784],"iteration":984,"passed_time":0.7838113634,"remaining_time":0.01193621366},
{"learn":[3.068801463],"iteration":985,"passed_time":0.7843766452,"remaining_time":0.01113719375},
{"learn":[3.067433249],"iteration":986,"passed_time":0.7849717641,"remaining_time":0.01033904046},
{"learn":[3.065611456],"iteration":987,"passed_time":0.785577293,"remaining_time":0.009541424611},
{"learn":[3.063039162],"iteration":988,"passed_time":0.7861904765,"remaining_time":0.008744282347},
{"learn":[3.06177873],"iteration":989,"passed_time":0.7867787423,"remaining_time":0.007947260023},
{"learn":[3.061689148],"iteration":990,"passed_time":0.7873735907,"remaining_time":0.007150718786},
{"learn":[3.058984039],"iteration":991,"passed_time":0.7879616461,"remaining_time":0.006354529404},
{"learn":[3.057492984],"iteration":992,"passed_time":0.788557246,"remaining_time":0.005558812409},
{"learn":[3.057290731],"iteration":993,"passed_time":0.7891727139,"remaining_time":0.004763617991},
{"learn":[3.056068348],"iteration":994,"passed_time":0.7897529543,"remaining_time":0.003968607811},
{"learn":[3.054987307],"iteration":995,"passed_time":0.790341641,"remaining_time":0.003174062815},
{"learn":[3.054200234],"iteration":996,"passed_time":0.7909549748,"remaining_time":0.002380004939},
{"learn":[3.052732869],"iteration":997,"passed_time":0.7916019129,"remaining_time":0.001586376579},
{"learn":[3.051787862],"iteration":998,"passed_time":0.7922402044,"remaining_time":0.0007930332377},
{"learn":[3.051366222],"iteration":999,"passed_time":0.7928384493,"remaining_time":0}
]}